Workbook

Sheet Calculator
A1: STAGGERED ORDER LADDER CALCULATOR
A3: INPUT PARAMETERS
A4: Total Budget ($) | B4: 10000 | C4: Total amount available for buy orders
A5: Current Price ($) | B5: 50 | C5: Current market price (highest buy rung)
A6: Profit Target (%) | B6: 75 | C6: Target profit percentage (10-200%)
A7: Number of Rungs | B7: 10 | C7: Number of buy/sell orders to place
A8: Buy Price Range (%) | B8: 30 | C8: Price range for buy ladder (0-100%)
A10: SUMMARY RESULTS
A11: Total Budget | B11: =$B$4
A12: Number of Rungs | B12: =$B$7
A13: Total Cost | B13: =SUM(F35:F54)
A14: Total Revenue | B14: =SUM(H60:H79)
A15: Total Profit | B15: =B14-B13
A16: Profit Percentage | B16: =IF(B13>0,(B15/B13)*100,0)
A17: Total Buy Quantity | B17: =SUM(G35:G54)
A18: Total Sell Quantity | B18: =SUM(G60:G79)
A20: VALIDATION STATUS
A21: VALIDATION STATUS
A22: See 'Helpers' sheet for detailed validation checks
A34: BUY ORDERS
A35: 1 | B35: =IF(1<=$B$7,'Helpers'!$B$6+('Helpers'!$B$5-'Helpers'!$B$6)*(1-1)/(IF($B$7>1,$B$7-1,1)),0) | C35: =IF(1<=$B$7,EXP(2-2*(1-1)/(IF($B$7>1,$B$7-1,1))),0) | D35: =IF(1<=$B$7,IF(SUM(C35:C54)>0,C35/SUM(C35:C54),0),0) | E35: =IF(1<=$B$7,IF(ISNUMBER(D35),$B$4*D35,0),0) | F35: =IF(1<=$B$7,IF(AND(ISNUMBER(E35),SUM(E35:E54)>0),E35*($B$4/SUM(E35:E54)),0),0) | G35: =IF(1<=$B$7,IF(B35>0,F35/B35,0),0) | H35: =F35 | I35: =G35 | J35: =IF(1<=$B$7,IF(I35>0,H35/I35,0),0) | K35: =IF(AND(A35<=$B$7,B35>0,G35>0,ISNUMBER(B35),ISNUMBER(G35)),"Yes","No")
A36: 2 | B36: =IF(2<=$B$7,'Helpers'!$B$6+('Helpers'!$B$5-'Helpers'!$B$6)*(2-1)/(IF($B$7>1,$B$7-1,1)),0) | C36: =IF(2<=$B$7,EXP(2-2*(2-1)/(IF($B$7>1,$B$7-1,1))),0) | D36: =IF(2<=$B$7,IF(SUM(C35:C54)>0,C36/SUM(C35:C54),0),0) | E36: =IF(2<=$B$7,IF(ISNUMBER(D36),$B$4*D36,0),0) | F36: =IF(2<=$B$7,IF(AND(ISNUMBER(E36),SUM(E35:E54)>0),E36*($B$4/SUM(E35:E54)),0),0) | G36: =IF(2<=$B$7,IF(B36>0,F36/B36,0),0) | H36: =IF(2<=$B$7,F36+H35,0) | I36: =IF(2<=$B$7,G36+I35,0) | J36: =IF(2<=$B$7,IF(I36>0,H36/I36,0),0) | K36: =IF(AND(A36<=$B$7,B36>0,G36>0,ISNUMBER(B36),ISNUMBER(G36)),"Yes","No")
A37: 3 | B37: =IF(3<=$B$7,'Helpers'!$B$6+('Helpers'!$B$5-'Helpers'!$B$6)*(3-1)/(IF($B$7>1,$B$7-1,1)),0) | C37: =IF(3<=$B$7,EXP(2-2*(3-1)/(IF($B$7>1,$B$7-1,1))),0) | D37: =IF(3<=$B$7,IF(SUM(C35:C54)>0,C37/SUM(C35:C54),0),0) | E37: =IF(3<=$B$7,IF(ISNUMBER(D37),$B$4*D37,0),0) | F37: =IF(3<=$B$7,IF(AND(ISNUMBER(E37),SUM(E35:E54)>0),E37*($B$4/SUM(E35:E54)),0),0) | G37: =IF(3<=$B$7,IF(B37>0,F37/B37,0),0) | H37: =IF(3<=$B$7,F37+H36,0) | I37: =IF(3<=$B$7,G37+I36,0) | J37: =IF(3<=$B$7,IF(I37>0,H37/I37,0),0) | K37: =IF(AND(A37<=$B$7,B37>0,G37>0,ISNUMBER(B37),ISNUMBER(G37)),"Yes","No")
A38: 4 | B38: =IF(4<=$B$7,'Helpers'!$B$6+('Helpers'!$B$5-'Helpers'!$B$6)*(4-1)/(IF($B$7>1,$B$7-1,1)),0) | C38: =IF(4<=$B$7,EXP(2-2*(4-1)/(IF($B$7>1,$B$7-1,1))),0) | D38: =IF(4<=$B$7,IF(SUM(C35:C54)>0,C38/SUM(C35:C54),0),0) | E38: =IF(4<=$B$7,IF(ISNUMBER(D38),$B$4*D38,0),0) | F38: =IF(4<=$B$7,IF(AND(ISNUMBER(E38),SUM(E35:E54)>0),E38*($B$4/SUM(E35:E54)),0),0) | G38: =IF(4<=$B$7,IF(B38>0,F38/B38,0),0) | H38: =IF(4<=$B$7,F38+H37,0) | I38: =IF(4<=$B$7,G38+I37,0) | J38: =IF(4<=$B$7,IF(I38>0,H38/I38,0),0) | K38: =IF(AND(A38<=$B$7,B38>0,G38>0,ISNUMBER(B38),ISNUMBER(G38)),"Yes","No")
A39: 5 | B39: =IF(5<=$B$7,'Helpers'!$B$6+('Helpers'!$B$5-'Helpers'!$B$6)*(5-1)/(IF($B$7>1,$B$7-1,1)),0) | C39: =IF(5<=$B$7,EXP(2-2*(5-1)/(IF($B$7>1,$B$7-1,1))),0) | D39: =IF(5<=$B$7,IF(SUM(C35:C54)>0,C39/SUM(C35:C54),0),0) | E39: =IF(5<=$B$7,IF(ISNUMBER(D39),$B$4*D39,0),0) | F39: =IF(5<=$B$7,IF(AND(ISNUMBER(E39),SUM(E35:E54)>0),E39*($B$4/SUM(E35:E54)),0),0) | G39: =IF(5<=$B$7,IF(B39>0,F39/B39,0),0) | H39: =IF(5<=$B$7,F39+H38,0) | I39: =IF(5<=$B$7,G39+I38,0) | J39: =IF(5<=$B$7,IF(I39>0,H39/I39,0),0) | K39: =IF(AND(A39<=$B$7,B39>0,G39>0,ISNUMBER(B39),ISNUMBER(G39)),"Yes","No")
A40: 6 | B40: =IF(6<=$B$7,'Helpers'!$B$6+('Helpers'!$B$5-'Helpers'!$B$6)*(6-1)/(IF($B$7>1,$B$7-1,1)),0) | C40: =IF(6<=$B$7,EXP(2-2*(6-1)/(IF($B$7>1,$B$7-1,1))),0) | D40: =IF(6<=$B$7,IF(SUM(C35:C54)>0,C40/SUM(C35:C54),0),0) | E40: =IF(6<=$B$7,IF(ISNUMBER(D40),$B$4*D40,0),0) | F40: =IF(6<=$B$7,IF(AND(ISNUMBER(E40),SUM(E35:E54)>0),E40*($B$4/SUM(E35:E54)),0),0) | G40: =IF(6<=$B$7,IF(B40>0,F40/B40,0),0) | H40: =IF(6<=$B$7,F40+H39,0) | I40: =IF(6<=$B$7,G40+I39,0) | J40: =IF(6<=$B$7,IF(I40>0,H40/I40,0),0) | K40: =IF(AND(A40<=$B$7,B40>0,G40>0,ISNUMBER(B40),ISNUMBER(G40)),"Yes","No")
A41: 7 | B41: =IF(7<=$B$7,'Helpers'!$B$6+('Helpers'!$B$5-'Helpers'!$B$6)*(7-1)/(IF($B$7>1,$B$7-1,1)),0) | C41: =IF(7<=$B$7,EXP(2-2*(7-1)/(IF($B$7>1,$B$7-1,1))),0) | D41: =IF(7<=$B$7,IF(SUM(C35:C54)>0,C41/SUM(C35:C54),0),0) | E41: =IF(7<=$B$7,IF(ISNUMBER(D41),$B$4*D41,0),0) | F41: =IF(7<=$B$7,IF(AND(ISNUMBER(E41),SUM(E35:E54)>0),E41*($B$4/SUM(E35:E54)),0),0) | G41: =IF(7<=$B$7,IF(B41>0,F41/B41,0),0) | H41: =IF(7<=$B$7,F41+H40,0) | I41: =IF(7<=$B$7,G41+I40,0) | J41: =IF(7<=$B$7,IF(I41>0,H41/I41,0),0) | K41: =IF(AND(A41<=$B$7,B41>0,G41>0,ISNUMBER(B41),ISNUMBER(G41)),"Yes","No")
A42: 8 | B42: =IF(8<=$B$7,'Helpers'!$B$6+('Helpers'!$B$5-'Helpers'!$B$6)*(8-1)/(IF($B$7>1,$B$7-1,1)),0) | C42: =IF(8<=$B$7,EXP(2-2*(8-1)/(IF($B$7>1,$B$7-1,1))),0) | D42: =IF(8<=$B$7,IF(SUM(C35:C54)>0,C42/SUM(C35:C54),0),0) | E42: =IF(8<=$B$7,IF(ISNUMBER(D42),$B$4*D42,0),0) | F42: =IF(8<=$B$7,IF(AND(ISNUMBER(E42),SUM(E35:E54)>0),E42*($B$4/SUM(E35:E54)),0),0) | G42: =IF(8<=$B$7,IF(B42>0,F42/B42,0),0) | H42: =IF(8<=$B$7,F42+H41,0) | I42: =IF(8<=$B$7,G42+I41,0) | J42: =IF(8<=$B$7,IF(I42>0,H42/I42,0),0) | K42: =IF(AND(A42<=$B$7,B42>0,G42>0,ISNUMBER(B42),ISNUMBER(G42)),"Yes","No")
A43: 9 | B43: =IF(9<=$B$7,'Helpers'!$B$6+('Helpers'!$B$5-'Helpers'!$B$6)*(9-1)/(IF($B$7>1,$B$7-1,1)),0) | C43: =IF(9<=$B$7,EXP(2-2*(9-1)/(IF($B$7>1,$B$7-1,1))),0) | D43: =IF(9<=$B$7,IF(SUM(C35:C54)>0,C43/SUM(C35:C54),0),0) | E43: =IF(9<=$B$7,IF(ISNUMBER(D43),$B$4*D43,0),0) | F43: =IF(9<=$B$7,IF(AND(ISNUMBER(E43),SUM(E35:E54)>0),E43*($B$4/SUM(E35:E54)),0),0) | G43: =IF(9<=$B$7,IF(B43>0,F43/B43,0),0) | H43: =IF(9<=$B$7,F43+H42,0) | I43: =IF(9<=$B$7,G43+I42,0) | J43: =IF(9<=$B$7,IF(I43>0,H43/I43,0),0) | K43: =IF(AND(A43<=$B$7,B43>0,G43>0,ISNUMBER(B43),ISNUMBER(G43)),"Yes","No")
A44: 10 | B44: =IF(10<=$B$7,'Helpers'!$B$6+('Helpers'!$B$5-'Helpers'!$B$6)*(10-1)/(IF($B$7>1,$B$7-1,1)),0) | C44: =IF(10<=$B$7,EXP(2-2*(10-1)/(IF($B$7>1,$B$7-1,1))),0) | D44: =IF(10<=$B$7,IF(SUM(C35:C54)>0,C44/SUM(C35:C54),0),0) | E44: =IF(10<=$B$7,IF(ISNUMBER(D44),$B$4*D44,0),0) | F44: =IF(10<=$B$7,IF(AND(ISNUMBER(E44),SUM(E35:E54)>0),E44*($B$4/SUM(E35:E54)),0),0) | G44: =IF(10<=$B$7,IF(B44>0,F44/B44,0),0) | H44: =IF(10<=$B$7,F44+H43,0) | I44: =IF(10<=$B$7,G44+I43,0) | J44: =IF(10<=$B$7,IF(I44>0,H44/I44,0),0) | K44: =IF(AND(A44<=$B$7,B44>0,G44>0,ISNUMBER(B44),ISNUMBER(G44)),"Yes","No")
A45: 11 | B45: =IF(11<=$B$7,'Helpers'!$B$6+('Helpers'!$B$5-'Helpers'!$B$6)*(11-1)/(IF($B$7>1,$B$7-1,1)),0) | C45: =IF(11<=$B$7,EXP(2-2*(11-1)/(IF($B$7>1,$B$7-1,1))),0) | D45: =IF(11<=$B$7,IF(SUM(C35:C54)>0,C45/SUM(C35:C54),0),0) | E45: =IF(11<=$B$7,IF(ISNUMBER(D45),$B$4*D45,0),0) | F45: =IF(11<=$B$7,IF(AND(ISNUMBER(E45),SUM(E35:E54)>0),E45*($B$4/SUM(E35:E54)),0),0) | G45: =IF(11<=$B$7,IF(B45>0,F45/B45,0),0) | H45: =IF(11<=$B$7,F45+H44,0) | I45: =IF(11<=$B$7,G45+I44,0) | J45: =IF(11<=$B$7,IF(I45>0,H45/I45,0),0) | K45: =IF(AND(A45<=$B$7,B45>0,G45>0,ISNUMBER(B45),ISNUMBER(G45)),"Yes","No")
A46: 12 | B46: =IF(12<=$B$7,'Helpers'!$B$6+('Helpers'!$B$5-'Helpers'!$B$6)*(12-1)/(IF($B$7>1,$B$7-1,1)),0) | C46: =IF(12<=$B$7,EXP(2-2*(12-1)/(IF($B$7>1,$B$7-1,1))),0) | D46: =IF(12<=$B$7,IF(SUM(C35:C54)>0,C46/SUM(C35:C54),0),0) | E46: =IF(12<=$B$7,IF(ISNUMBER(D46),$B$4*D46,0),0) | F46: =IF(12<=$B$7,IF(AND(ISNUMBER(E46),SUM(E35:E54)>0),E46*($B$4/SUM(E35:E54)),0),0) | G46: =IF(12<=$B$7,IF(B46>0,F46/B46,0),0) | H46: =IF(12<=$B$7,F46+H45,0) | I46: =IF(12<=$B$7,G46+I45,0) | J46: =IF(12<=$B$7,IF(I46>0,H46/I46,0),0) | K46: =IF(AND(A46<=$B$7,B46>0,G46>0,ISNUMBER(B46),ISNUMBER(G46)),"Yes","No")
A47: 13 | B47: =IF(13<=$B$7,'Helpers'!$B$6+('Helpers'!$B$5-'Helpers'!$B$6)*(13-1)/(IF($B$7>1,$B$7-1,1)),0) | C47: =IF(13<=$B$7,EXP(2-2*(13-1)/(IF($B$7>1,$B$7-1,1))),0) | D47: =IF(13<=$B$7,IF(SUM(C35:C54)>0,C47/SUM(C35:C54),0),0) | E47: =IF(13<=$B$7,IF(ISNUMBER(D47),$B$4*D47,0),0) | F47: =IF(13<=$B$7,IF(AND(ISNUMBER(E47),SUM(E35:E54)>0),E47*($B$4/SUM(E35:E54)),0),0) | G47: =IF(13<=$B$7,IF(B47>0,F47/B47,0),0) | H47: =IF(13<=$B$7,F47+H46,0) | I47: =IF(13<=$B$7,G47+I46,0) | J47: =IF(13<=$B$7,IF(I47>0,H47/I47,0),0) | K47: =IF(AND(A47<=$B$7,B47>0,G47>0,ISNUMBER(B47),ISNUMBER(G47)),"Yes","No")
A48: 14 | B48: =IF(14<=$B$7,'Helpers'!$B$6+('Helpers'!$B$5-'Helpers'!$B$6)*(14-1)/(IF($B$7>1,$B$7-1,1)),0) | C48: =IF(14<=$B$7,EXP(2-2*(14-1)/(IF($B$7>1,$B$7-1,1))),0) | D48: =IF(14<=$B$7,IF(SUM(C35:C54)>0,C48/SUM(C35:C54),0),0) | E48: =IF(14<=$B$7,IF(ISNUMBER(D48),$B$4*D48,0),0) | F48: =IF(14<=$B$7,IF(AND(ISNUMBER(E48),SUM(E35:E54)>0),E48*($B$4/SUM(E35:E54)),0),0) | G48: =IF(14<=$B$7,IF(B48>0,F48/B48,0),0) | H48: =IF(14<=$B$7,F48+H47,0) | I48: =IF(14<=$B$7,G48+I47,0) | J48: =IF(14<=$B$7,IF(I48>0,H48/I48,0),0) | K48: =IF(AND(A48<=$B$7,B48>0,G48>0,ISNUMBER(B48),ISNUMBER(G48)),"Yes","No")
A49: 15 | B49: =IF(15<=$B$7,'Helpers'!$B$6+('Helpers'!$B$5-'Helpers'!$B$6)*(15-1)/(IF($B$7>1,$B$7-1,1)),0) | C49: =IF(15<=$B$7,EXP(2-2*(15-1)/(IF($B$7>1,$B$7-1,1))),0) | D49: =IF(15<=$B$7,IF(SUM(C35:C54)>0,C49/SUM(C35:C54),0),0) | E49: =IF(15<=$B$7,IF(ISNUMBER(D49),$B$4*D49,0),0) | F49: =IF(15<=$B$7,IF(AND(ISNUMBER(E49),SUM(E35:E54)>0),E49*($B$4/SUM(E35:E54)),0),0) | G49: =IF(15<=$B$7,IF(B49>0,F49/B49,0),0) | H49: =IF(15<=$B$7,F49+H48,0) | I49: =IF(15<=$B$7,G49+I48,0) | J49: =IF(15<=$B$7,IF(I49>0,H49/I49,0),0) | K49: =IF(AND(A49<=$B$7,B49>0,G49>0,ISNUMBER(B49),ISNUMBER(G49)),"Yes","No")
A50: 16 | B50: =IF(16<=$B$7,'Helpers'!$B$6+('Helpers'!$B$5-'Helpers'!$B$6)*(16-1)/(IF($B$7>1,$B$7-1,1)),0) | C50: =IF(16<=$B$7,EXP(2-2*(16-1)/(IF($B$7>1,$B$7-1,1))),0) | D50: =IF(16<=$B$7,IF(SUM(C35:C54)>0,C50/SUM(C35:C54),0),0) | E50: =IF(16<=$B$7,IF(ISNUMBER(D50),$B$4*D50,0),0) | F50: =IF(16<=$B$7,IF(AND(ISNUMBER(E50),SUM(E35:E54)>0),E50*($B$4/SUM(E35:E54)),0),0) | G50: =IF(16<=$B$7,IF(B50>0,F50/B50,0),0) | H50: =IF(16<=$B$7,F50+H49,0) | I50: =IF(16<=$B$7,G50+I49,0) | J50: =IF(16<=$B$7,IF(I50>0,H50/I50,0),0) | K50: =IF(AND(A50<=$B$7,B50>0,G50>0,ISNUMBER(B50),ISNUMBER(G50)),"Yes","No")
A51: 17 | B51: =IF(17<=$B$7,'Helpers'!$B$6+('Helpers'!$B$5-'Helpers'!$B$6)*(17-1)/(IF($B$7>1,$B$7-1,1)),0) | C51: =IF(17<=$B$7,EXP(2-2*(17-1)/(IF($B$7>1,$B$7-1,1))),0) | D51: =IF(17<=$B$7,IF(SUM(C35:C54)>0,C51/SUM(C35:C54),0),0) | E51: =IF(17<=$B$7,IF(ISNUMBER(D51),$B$4*D51,0),0) | F51: =IF(17<=$B$7,IF(AND(ISNUMBER(E51),SUM(E35:E54)>0),E51*($B$4/SUM(E35:E54)),0),0) | G51: =IF(17<=$B$7,IF(B51>0,F51/B51,0),0) | H51: =IF(17<=$B$7,F51+H50,0) | I51: =IF(17<=$B$7,G51+I50,0) | J51: =IF(17<=$B$7,IF(I51>0,H51/I51,0),0) | K51: =IF(AND(A51<=$B$7,B51>0,G51>0,ISNUMBER(B51),ISNUMBER(G51)),"Yes","No")
A52: 18 | B52: =IF(18<=$B$7,'Helpers'!$B$6+('Helpers'!$B$5-'Helpers'!$B$6)*(18-1)/(IF($B$7>1,$B$7-1,1)),0) | C52: =IF(18<=$B$7,EXP(2-2*(18-1)/(IF($B$7>1,$B$7-1,1))),0) | D52: =IF(18<=$B$7,IF(SUM(C35:C54)>0,C52/SUM(C35:C54),0),0) | E52: =IF(18<=$B$7,IF(ISNUMBER(D52),$B$4*D52,0),0) | F52: =IF(18<=$B$7,IF(AND(ISNUMBER(E52),SUM(E35:E54)>0),E52*($B$4/SUM(E35:E54)),0),0) | G52: =IF(18<=$B$7,IF(B52>0,F52/B52,0),0) | H52: =IF(18<=$B$7,F52+H51,0) | I52: =IF(18<=$B$7,G52+I51,0) | J52: =IF(18<=$B$7,IF(I52>0,H52/I52,0),0) | K52: =IF(AND(A52<=$B$7,B52>0,G52>0,ISNUMBER(B52),ISNUMBER(G52)),"Yes","No")
A53: 19 | B53: =IF(19<=$B$7,'Helpers'!$B$6+('Helpers'!$B$5-'Helpers'!$B$6)*(19-1)/(IF($B$7>1,$B$7-1,1)),0) | C53: =IF(19<=$B$7,EXP(2-2*(19-1)/(IF($B$7>1,$B$7-1,1))),0) | D53: =IF(19<=$B$7,IF(SUM(C35:C54)>0,C53/SUM(C35:C54),0),0) | E53: =IF(19<=$B$7,IF(ISNUMBER(D53),$B$4*D53,0),0) | F53: =IF(19<=$B$7,IF(AND(ISNUMBER(E53),SUM(E35:E54)>0),E53*($B$4/SUM(E35:E54)),0),0) | G53: =IF(19<=$B$7,IF(B53>0,F53/B53,0),0) | H53: =IF(19<=$B$7,F53+H52,0) | I53: =IF(19<=$B$7,G53+I52,0) | J53: =IF(19<=$B$7,IF(I53>0,H53/I53,0),0) | K53: =IF(AND(A53<=$B$7,B53>0,G53>0,ISNUMBER(B53),ISNUMBER(G53)),"Yes","No")
A54: 20 | B54: =IF(20<=$B$7,'Helpers'!$B$6+('Helpers'!$B$5-'Helpers'!$B$6)*(20-1)/(IF($B$7>1,$B$7-1,1)),0) | C54: =IF(20<=$B$7,EXP(2-2*(20-1)/(IF($B$7>1,$B$7-1,1))),0) | D54: =IF(20<=$B$7,IF(SUM(C35:C54)>0,C54/SUM(C35:C54),0),0) | E54: =IF(20<=$B$7,IF(ISNUMBER(D54),$B$4*D54,0),0) | F54: =IF(20<=$B$7,IF(AND(ISNUMBER(E54),SUM(E35:E54)>0),E54*($B$4/SUM(E35:E54)),0),0) | G54: =IF(20<=$B$7,IF(B54>0,F54/B54,0),0) | H54: =IF(20<=$B$7,F54+H53,0) | I54: =IF(20<=$B$7,G54+I53,0) | J54: =IF(20<=$B$7,IF(I54>0,H54/I54,0),0) | K54: =IF(AND(A54<=$B$7,B54>0,G54>0,ISNUMBER(B54),ISNUMBER(G54)),"Yes","No")
A59: SELL ORDERS
A60: 1 | B60: =IF(1<=$B$7,'Helpers'!$B$10+'Helpers'!$B$7*(1-1),0) | C60: =IF(1<=$B$7,MAX(B60*'Helpers'!$B$19,'Helpers'!$B$20+'Helpers'!$B$7*(1-1)),0) | D60: =IF(1<=$B$7,EXP(2*(1-1)/(IF($B$7>1,$B$7-1,1))),0) | E60: =IF(1<=$B$7,IF(SUM(D60:D79)>0,D60/SUM(D60:D79),0),0) | F60: =IF(1<=$B$7,'Helpers'!$B$13*E60,0) | G60: =IF(1<=$B$7,IF(AND(ISNUMBER(F60),SUM(F60:F79)>0,'Helpers'!$B$13>0),F60*('Helpers'!$B$13/SUM(F60:F79)),0),0) | H60: =IF(1<=$B$7,C60*G60,0) | I60: =H60 | J60: =G60 | K60: =IF(1<=$B$7,IF(J60>0,I60/J60,0),0) | L60: =IF(AND(A60<=$B$7,C60>0,G60>0,ISNUMBER(C60),ISNUMBER(G60)),"Yes","No")
A61: 2 | B61: =IF(2<=$B$7,'Helpers'!$B$10+'Helpers'!$B$7*(2-1),0) | C61: =IF(2<=$B$7,MAX(B61*'Helpers'!$B$19,'Helpers'!$B$20+'Helpers'!$B$7*(2-1)),0) | D61: =IF(2<=$B$7,EXP(2*(2-1)/(IF($B$7>1,$B$7-1,1))),0) | E61: =IF(2<=$B$7,IF(SUM(D60:D79)>0,D61/SUM(D60:D79),0),0) | F61: =IF(2<=$B$7,'Helpers'!$B$13*E61,0) | G61: =IF(2<=$B$7,IF(AND(ISNUMBER(F61),SUM(F60:F79)>0,'Helpers'!$B$13>0),F61*('Helpers'!$B$13/SUM(F60:F79)),0),0) | H61: =IF(2<=$B$7,C61*G61,0) | I61: =IF(2<=$B$7,H61+I60,0) | J61: =IF(2<=$B$7,G61+J60,0) | K61: =IF(2<=$B$7,IF(J61>0,I61/J61,0),0) | L61: =IF(AND(A61<=$B$7,C61>0,G61>0,ISNUMBER(C61),ISNUMBER(G61)),"Yes","No")
A62: 3 | B62: =IF(3<=$B$7,'Helpers'!$B$10+'Helpers'!$B$7*(3-1),0) | C62: =IF(3<=$B$7,MAX(B62*'Helpers'!$B$19,'Helpers'!$B$20+'Helpers'!$B$7*(3-1)),0) | D62: =IF(3<=$B$7,EXP(2*(3-1)/(IF($B$7>1,$B$7-1,1))),0) | E62: =IF(3<=$B$7,IF(SUM(D60:D79)>0,D62/SUM(D60:D79),0),0) | F62: =IF(3<=$B$7,'Helpers'!$B$13*E62,0) | G62: =IF(3<=$B$7,IF(AND(ISNUMBER(F62),SUM(F60:F79)>0,'Helpers'!$B$13>0),F62*('Helpers'!$B$13/SUM(F60:F79)),0),0) | H62: =IF(3<=$B$7,C62*G62,0) | I62: =IF(3<=$B$7,H62+I61,0) | J62: =IF(3<=$B$7,G62+J61,0) | K62: =IF(3<=$B$7,IF(J62>0,I62/J62,0),0) | L62: =IF(AND(A62<=$B$7,C62>0,G62>0,ISNUMBER(C62),ISNUMBER(G62)),"Yes","No")
A63: 4 | B63: =IF(4<=$B$7,'Helpers'!$B$10+'Helpers'!$B$7*(4-1),0) | C63: =IF(4<=$B$7,MAX(B63*'Helpers'!$B$19,'Helpers'!$B$20+'Helpers'!$B$7*(4-1)),0) | D63: =IF(4<=$B$7,EXP(2*(4-1)/(IF($B$7>1,$B$7-1,1))),0) | E63: =IF(4<=$B$7,IF(SUM(D60:D79)>0,D63/SUM(D60:D79),0),0) | F63: =IF(4<=$B$7,'Helpers'!$B$13*E63,0) | G63: =IF(4<=$B$7,IF(AND(ISNUMBER(F63),SUM(F60:F79)>0,'Helpers'!$B$13>0),F63*('Helpers'!$B$13/SUM(F60:F79)),0),0) | H63: =IF(4<=$B$7,C63*G63,0) | I63: =IF(4<=$B$7,H63+I62,0) | J63: =IF(4<=$B$7,G63+J62,0) | K63: =IF(4<=$B$7,IF(J63>0,I63/J63,0),0) | L63: =IF(AND(A63<=$B$7,C63>0,G63>0,ISNUMBER(C63),ISNUMBER(G63)),"Yes","No")
A64: 5 | B64: =IF(5<=$B$7,'Helpers'!$B$10+'Helpers'!$B$7*(5-1),0) | C64: =IF(5<=$B$7,MAX(B64*'Helpers'!$B$19,'Helpers'!$B$20+'Helpers'!$B$7*(5-1)),0) | D64: =IF(5<=$B$7,EXP(2*(5-1)/(IF($B$7>1,$B$7-1,1))),0) | E64: =IF(5<=$B$7,IF(SUM(D60:D79)>0,D64/SUM(D60:D79),0),0) | F64: =IF(5<=$B$7,'Helpers'!$B$13*E64,0) | G64: =IF(5<=$B$7,IF(AND(ISNUMBER(F64),SUM(F60:F79)>0,'Helpers'!$B$13>0),F64*('Helpers'!$B$13/SUM(F60:F79)),0),0) | H64: =IF(5<=$B$7,C64*G64,0) | I64: =IF(5<=$B$7,H64+I63,0) | J64: =IF(5<=$B$7,G64+J63,0) | K64: =IF(5<=$B$7,IF(J64>0,I64/J64,0),0) | L64: =IF(AND(A64<=$B$7,C64>0,G64>0,ISNUMBER(C64),ISNUMBER(G64)),"Yes","No")
A65: 6 | B65: =IF(6<=$B$7,'Helpers'!$B$10+'Helpers'!$B$7*(6-1),0) | C65: =IF(6<=$B$7,MAX(B65*'Helpers'!$B$19,'Helpers'!$B$20+'Helpers'!$B$7*(6-1)),0) | D65: =IF(6<=$B$7,EXP(2*(6-1)/(IF($B$7>1,$B$7-1,1))),0) | E65: =IF(6<=$B$7,IF(SUM(D60:D79)>0,D65/SUM(D60:D79),0),0) | F65: =IF(6<=$B$7,'Helpers'!$B$13*E65,0) | G65: =IF(6<=$B$7,IF(AND(ISNUMBER(F65),SUM(F60:F79)>0,'Helpers'!$B$13>0),F65*('Helpers'!$B$13/SUM(F60:F79)),0),0) | H65: =IF(6<=$B$7,C65*G65,0) | I65: =IF(6<=$B$7,H65+I64,0) | J65: =IF(6<=$B$7,G65+J64,0) | K65: =IF(6<=$B$7,IF(J65>0,I65/J65,0),0) | L65: =IF(AND(A65<=$B$7,C65>0,G65>0,ISNUMBER(C65),ISNUMBER(G65)),"Yes","No")
A66: 7 | B66: =IF(7<=$B$7,'Helpers'!$B$10+'Helpers'!$B$7*(7-1),0) | C66: =IF(7<=$B$7,MAX(B66*'Helpers'!$B$19,'Helpers'!$B$20+'Helpers'!$B$7*(7-1)),0) | D66: =IF(7<=$B$7,EXP(2*(7-1)/(IF($B$7>1,$B$7-1,1))),0) | E66: =IF(7<=$B$7,IF(SUM(D60:D79)>0,D66/SUM(D60:D79),0),0) | F66: =IF(7<=$B$7,'Helpers'!$B$13*E66,0) | G66: =IF(7<=$B$7,IF(AND(ISNUMBER(F66),SUM(F60:F79)>0,'Helpers'!$B$13>0),F66*('Helpers'!$B$13/SUM(F60:F79)),0),0) | H66: =IF(7<=$B$7,C66*G66,0) | I66: =IF(7<=$B$7,H66+I65,0) | J66: =IF(7<=$B$7,G66+J65,0) | K66: =IF(7<=$B$7,IF(J66>0,I66/J66,0),0) | L66: =IF(AND(A66<=$B$7,C66>0,G66>0,ISNUMBER(C66),ISNUMBER(G66)),"Yes","No")
A67: 8 | B67: =IF(8<=$B$7,'Helpers'!$B$10+'Helpers'!$B$7*(8-1),0) | C67: =IF(8<=$B$7,MAX(B67*'Helpers'!$B$19,'Helpers'!$B$20+'Helpers'!$B$7*(8-1)),0) | D67: =IF(8<=$B$7,EXP(2*(8-1)/(IF($B$7>1,$B$7-1,1))),0) | E67: =IF(8<=$B$7,IF(SUM(D60:D79)>0,D67/SUM(D60:D79),0),0) | F67: =IF(8<=$B$7,'Helpers'!$B$13*E67,0) | G67: =IF(8<=$B$7,IF(AND(ISNUMBER(F67),SUM(F60:F79)>0,'Helpers'!$B$13>0),F67*('Helpers'!$B$13/SUM(F60:F79)),0),0) | H67: =IF(8<=$B$7,C67*G67,0) | I67: =IF(8<=$B$7,H67+I66,0) | J67: =IF(8<=$B$7,G67+J66,0) | K67: =IF(8<=$B$7,IF(J67>0,I67/J67,0),0) | L67: =IF(AND(A67<=$B$7,C67>0,G67>0,ISNUMBER(C67),ISNUMBER(G67)),"Yes","No")
A68: 9 | B68: =IF(9<=$B$7,'Helpers'!$B$10+'Helpers'!$B$7*(9-1),0) | C68: =IF(9<=$B$7,MAX(B68*'Helpers'!$B$19,'Helpers'!$B$20+'Helpers'!$B$7*(9-1)),0) | D68: =IF(9<=$B$7,EXP(2*(9-1)/(IF($B$7>1,$B$7-1,1))),0) | E68: =IF(9<=$B$7,IF(SUM(D60:D79)>0,D68/SUM(D60:D79),0),0) | F68: =IF(9<=$B$7,'Helpers'!$B$13*E68,0) | G68: =IF(9<=$B$7,IF(AND(ISNUMBER(F68),SUM(F60:F79)>0,'Helpers'!$B$13>0),F68*('Helpers'!$B$13/SUM(F60:F79)),0),0) | H68: =IF(9<=$B$7,C68*G68,0) | I68: =IF(9<=$B$7,H68+I67,0) | J68: =IF(9<=$B$7,G68+J67,0) | K68: =IF(9<=$B$7,IF(J68>0,I68/J68,0),0) | L68: =IF(AND(A68<=$B$7,C68>0,G68>0,ISNUMBER(C68),ISNUMBER(G68)),"Yes","No")
A69: 10 | B69: =IF(10<=$B$7,'Helpers'!$B$10+'Helpers'!$B$7*(10-1),0) | C69: =IF(10<=$B$7,MAX(B69*'Helpers'!$B$19,'Helpers'!$B$20+'Helpers'!$B$7*(10-1)),0) | D69: =IF(10<=$B$7,EXP(2*(10-1)/(IF($B$7>1,$B$7-1,1))),0) | E69: =IF(10<=$B$7,IF(SUM(D60:D79)>0,D69/SUM(D60:D79),0),0) | F69: =IF(10<=$B$7,'Helpers'!$B$13*E69,0) | G69: =IF(10<=$B$7,IF(AND(ISNUMBER(F69),SUM(F60:F79)>0,'Helpers'!$B$13>0),F69*('Helpers'!$B$13/SUM(F60:F79)),0),0) | H69: =IF(10<=$B$7,C69*G69,0) | I69: =IF(10<=$B$7,H69+I68,0) | J69: =IF(10<=$B$7,G69+J68,0) | K69: =IF(10<=$B$7,IF(J69>0,I69/J69,0),0) | L69: =IF(AND(A69<=$B$7,C69>0,G69>0,ISNUMBER(C69),ISNUMBER(G69)),"Yes","No")
A70: 11 | B70: =IF(11<=$B$7,'Helpers'!$B$10+'Helpers'!$B$7*(11-1),0) | C70: =IF(11<=$B$7,MAX(B70*'Helpers'!$B$19,'Helpers'!$B$20+'Helpers'!$B$7*(11-1)),0) | D70: =IF(11<=$B$7,EXP(2*(11-1)/(IF($B$7>1,$B$7-1,1))),0) | E70: =IF(11<=$B$7,IF(SUM(D60:D79)>0,D70/SUM(D60:D79),0),0) | F70: =IF(11<=$B$7,'Helpers'!$B$13*E70,0) | G70: =IF(11<=$B$7,IF(AND(ISNUMBER(F70),SUM(F60:F79)>0,'Helpers'!$B$13>0),F70*('Helpers'!$B$13/SUM(F60:F79)),0),0) | H70: =IF(11<=$B$7,C70*G70,0) | I70: =IF(11<=$B$7,H70+I69,0) | J70: =IF(11<=$B$7,G70+J69,0) | K70: =IF(11<=$B$7,IF(J70>0,I70/J70,0),0) | L70: =IF(AND(A70<=$B$7,C70>0,G70>0,ISNUMBER(C70),ISNUMBER(G70)),"Yes","No")
A71: 12 | B71: =IF(12<=$B$7,'Helpers'!$B$10+'Helpers'!$B$7*(12-1),0) | C71: =IF(12<=$B$7,MAX(B71*'Helpers'!$B$19,'Helpers'!$B$20+'Helpers'!$B$7*(12-1)),0) | D71: =IF(12<=$B$7,EXP(2*(12-1)/(IF($B$7>1,$B$7-1,1))),0) | E71: =IF(12<=$B$7,IF(SUM(D60:D79)>0,D71/SUM(D60:D79),0),0) | F71: =IF(12<=$B$7,'Helpers'!$B$13*E71,0) | G71: =IF(12<=$B$7,IF(AND(ISNUMBER(F71),SUM(F60:F79)>0,'Helpers'!$B$13>0),F71*('Helpers'!$B$13/SUM(F60:F79)),0),0) | H71: =IF(12<=$B$7,C71*G71,0) | I71: =IF(12<=$B$7,H71+I70,0) | J71: =IF(12<=$B$7,G71+J70,0) | K71: =IF(12<=$B$7,IF(J71>0,I71/J71,0),0) | L71: =IF(AND(A71<=$B$7,C71>0,G71>0,ISNUMBER(C71),ISNUMBER(G71)),"Yes","No")
A72: 13 | B72: =IF(13<=$B$7,'Helpers'!$B$10+'Helpers'!$B$7*(13-1),0) | C72: =IF(13<=$B$7,MAX(B72*'Helpers'!$B$19,'Helpers'!$B$20+'Helpers'!$B$7*(13-1)),0) | D72: =IF(13<=$B$7,EXP(2*(13-1)/(IF($B$7>1,$B$7-1,1))),0) | E72: =IF(13<=$B$7,IF(SUM(D60:D79)>0,D72/SUM(D60:D79),0),0) | F72: =IF(13<=$B$7,'Helpers'!$B$13*E72,0) | G72: =IF(13<=$B$7,IF(AND(ISNUMBER(F72),SUM(F60:F79)>0,'Helpers'!$B$13>0),F72*('Helpers'!$B$13/SUM(F60:F79)),0),0) | H72: =IF(13<=$B$7,C72*G72,0) | I72: =IF(13<=$B$7,H72+I71,0) | J72: =IF(13<=$B$7,G72+J71,0) | K72: =IF(13<=$B$7,IF(J72>0,I72/J72,0),0) | L72: =IF(AND(A72<=$B$7,C72>0,G72>0,ISNUMBER(C72),ISNUMBER(G72)),"Yes","No")
A73: 14 | B73: =IF(14<=$B$7,'Helpers'!$B$10+'Helpers'!$B$7*(14-1),0) | C73: =IF(14<=$B$7,MAX(B73*'Helpers'!$B$19,'Helpers'!$B$20+'Helpers'!$B$7*(14-1)),0) | D73: =IF(14<=$B$7,EXP(2*(14-1)/(IF($B$7>1,$B$7-1,1))),0) | E73: =IF(14<=$B$7,IF(SUM(D60:D79)>0,D73/SUM(D60:D79),0),0) | F73: =IF(14<=$B$7,'Helpers'!$B$13*E73,0) | G73: =IF(14<=$B$7,IF(AND(ISNUMBER(F73),SUM(F60:F79)>0,'Helpers'!$B$13>0),F73*('Helpers'!$B$13/SUM(F60:F79)),0),0) | H73: =IF(14<=$B$7,C73*G73,0) | I73: =IF(14<=$B$7,H73+I72,0) | J73: =IF(14<=$B$7,G73+J72,0) | K73: =IF(14<=$B$7,IF(J73>0,I73/J73,0),0) | L73: =IF(AND(A73<=$B$7,C73>0,G73>0,ISNUMBER(C73),ISNUMBER(G73)),"Yes","No")
A74: 15 | B74: =IF(15<=$B$7,'Helpers'!$B$10+'Helpers'!$B$7*(15-1),0) | C74: =IF(15<=$B$7,MAX(B74*'Helpers'!$B$19,'Helpers'!$B$20+'Helpers'!$B$7*(15-1)),0) | D74: =IF(15<=$B$7,EXP(2*(15-1)/(IF($B$7>1,$B$7-1,1))),0) | E74: =IF(15<=$B$7,IF(SUM(D60:D79)>0,D74/SUM(D60:D79),0),0) | F74: =IF(15<=$B$7,'Helpers'!$B$13*E74,0) | G74: =IF(15<=$B$7,IF(AND(ISNUMBER(F74),SUM(F60:F79)>0,'Helpers'!$B$13>0),F74*('Helpers'!$B$13/SUM(F60:F79)),0),0) | H74: =IF(15<=$B$7,C74*G74,0) | I74: =IF(15<=$B$7,H74+I73,0) | J74: =IF(15<=$B$7,G74+J73,0) | K74: =IF(15<=$B$7,IF(J74>0,I74/J74,0),0) | L74: =IF(AND(A74<=$B$7,C74>0,G74>0,ISNUMBER(C74),ISNUMBER(G74)),"Yes","No")
A75: 16 | B75: =IF(16<=$B$7,'Helpers'!$B$10+'Helpers'!$B$7*(16-1),0) | C75: =IF(16<=$B$7,MAX(B75*'Helpers'!$B$19,'Helpers'!$B$20+'Helpers'!$B$7*(16-1)),0) | D75: =IF(16<=$B$7,EXP(2*(16-1)/(IF($B$7>1,$B$7-1,1))),0) | E75: =IF(16<=$B$7,IF(SUM(D60:D79)>0,D75/SUM(D60:D79),0),0) | F75: =IF(16<=$B$7,'Helpers'!$B$13*E75,0) | G75: =IF(16<=$B$7,IF(AND(ISNUMBER(F75),SUM(F60:F79)>0,'Helpers'!$B$13>0),F75*('Helpers'!$B$13/SUM(F60:F79)),0),0) | H75: =IF(16<=$B$7,C75*G75,0) | I75: =IF(16<=$B$7,H75+I74,0) | J75: =IF(16<=$B$7,G75+J74,0) | K75: =IF(16<=$B$7,IF(J75>0,I75/J75,0),0) | L75: =IF(AND(A75<=$B$7,C75>0,G75>0,ISNUMBER(C75),ISNUMBER(G75)),"Yes","No")
A76: 17 | B76: =IF(17<=$B$7,'Helpers'!$B$10+'Helpers'!$B$7*(17-1),0) | C76: =IF(17<=$B$7,MAX(B76*'Helpers'!$B$19,'Helpers'!$B$20+'Helpers'!$B$7*(17-1)),0) | D76: =IF(17<=$B$7,EXP(2*(17-1)/(IF($B$7>1,$B$7-1,1))),0) | E76: =IF(17<=$B$7,IF(SUM(D60:D79)>0,D76/SUM(D60:D79),0),0) | F76: =IF(17<=$B$7,'Helpers'!$B$13*E76,0) | G76: =IF(17<=$B$7,IF(AND(ISNUMBER(F76),SUM(F60:F79)>0,'Helpers'!$B$13>0),F76*('Helpers'!$B$13/SUM(F60:F79)),0),0) | H76: =IF(17<=$B$7,C76*G76,0) | I76: =IF(17<=$B$7,H76+I75,0) | J76: =IF(17<=$B$7,G76+J75,0) | K76: =IF(17<=$B$7,IF(J76>0,I76/J76,0),0) | L76: =IF(AND(A76<=$B$7,C76>0,G76>0,ISNUMBER(C76),ISNUMBER(G76)),"Yes","No")
A77: 18 | B77: =IF(18<=$B$7,'Helpers'!$B$10+'Helpers'!$B$7*(18-1),0) | C77: =IF(18<=$B$7,MAX(B77*'Helpers'!$B$19,'Helpers'!$B$20+'Helpers'!$B$7*(18-1)),0) | D77: =IF(18<=$B$7,EXP(2*(18-1)/(IF($B$7>1,$B$7-1,1))),0) | E77: =IF(18<=$B$7,IF(SUM(D60:D79)>0,D77/SUM(D60:D79),0),0) | F77: =IF(18<=$B$7,'Helpers'!$B$13*E77,0) | G77: =IF(18<=$B$7,IF(AND(ISNUMBER(F77),SUM(F60:F79)>0,'Helpers'!$B$13>0),F77*('Helpers'!$B$13/SUM(F60:F79)),0),0) | H77: =IF(18<=$B$7,C77*G77,0) | I77: =IF(18<=$B$7,H77+I76,0) | J77: =IF(18<=$B$7,G77+J76,0) | K77: =IF(18<=$B$7,IF(J77>0,I77/J77,0),0) | L77: =IF(AND(A77<=$B$7,C77>0,G77>0,ISNUMBER(C77),ISNUMBER(G77)),"Yes","No")
A78: 19 | B78: =IF(19<=$B$7,'Helpers'!$B$10+'Helpers'!$B$7*(19-1),0) | C78: =IF(19<=$B$7,MAX(B78*'Helpers'!$B$19,'Helpers'!$B$20+'Helpers'!$B$7*(19-1)),0) | D78: =IF(19<=$B$7,EXP(2*(19-1)/(IF($B$7>1,$B$7-1,1))),0) | E78: =IF(19<=$B$7,IF(SUM(D60:D79)>0,D78/SUM(D60:D79),0),0) | F78: =IF(19<=$B$7,'Helpers'!$B$13*E78,0) | G78: =IF(19<=$B$7,IF(AND(ISNUMBER(F78),SUM(F60:F79)>0,'Helpers'!$B$13>0),F78*('Helpers'!$B$13/SUM(F60:F79)),0),0) | H78: =IF(19<=$B$7,C78*G78,0) | I78: =IF(19<=$B$7,H78+I77,0) | J78: =IF(19<=$B$7,G78+J77,0) | K78: =IF(19<=$B$7,IF(J78>0,I78/J78,0),0) | L78: =IF(AND(A78<=$B$7,C78>0,G78>0,ISNUMBER(C78),ISNUMBER(G78)),"Yes","No")
A79: 20 | B79: =IF(20<=$B$7,'Helpers'!$B$10+'Helpers'!$B$7*(20-1),0) | C79: =IF(20<=$B$7,MAX(B79*'Helpers'!$B$19,'Helpers'!$B$20+'Helpers'!$B$7*(20-1)),0) | D79: =IF(20<=$B$7,EXP(2*(20-1)/(IF($B$7>1,$B$7-1,1))),0) | E79: =IF(20<=$B$7,IF(SUM(D60:D79)>0,D79/SUM(D60:D79),0),0) | F79: =IF(20<=$B$7,'Helpers'!$B$13*E79,0) | G79: =IF(20<=$B$7,IF(AND(ISNUMBER(F79),SUM(F60:F79)>0,'Helpers'!$B$13>0),F79*('Helpers'!$B$13/SUM(F60:F79)),0),0) | H79: =IF(20<=$B$7,C79*G79,0) | I79: =IF(20<=$B$7,H79+I78,0) | J79: =IF(20<=$B$7,G79+J78,0) | K79: =IF(20<=$B$7,IF(J79>0,I79/J79,0),0) | L79: =IF(AND(A79<=$B$7,C79>0,G79>0,ISNUMBER(C79),ISNUMBER(G79)),"Yes","No")
A85: INSTRUCTIONS
A86: 1. Enter your parameters in the INPUT PARAMETERS section at the top.
A87: 2. Review the SUMMARY RESULTS to see total cost, revenue, and profit.
A88: 3. Check VALIDATION STATUS to ensure all inputs are valid.
A89: 4. View BUY ORDERS and SELL ORDERS tables below.
A90: 5. Filters are applied automatically - only active rungs are shown.
A91: 6. See the Charts sheet for visualizations.
A92: 7. Helper calculations are hidden but can be viewed by unhiding columns.

Sheet Helpers
A1: HELPER CALCULATIONS
A2: ⚠ WARNING: These cells are protected. Modifying them may cause calculation errors.
A4: Buy Price Helpers
A5: Buy Upper | B5: ='Calculator'!$B$5
A6: Buy Lower | B6: =IF('Calculator'!$B$5>0,'Calculator'!$B$5*(1-'Calculator'!$B$8/100),0)
A7: Price Step | B7: =IF(AND('Calculator'!$B$7>1,B5>0,B6>0),(B5-B6)/('Calculator'!$B$7-1),IF('Calculator'!$B$5>0,'Calculator'!$B$5*0.1,0))
A8: Max Buy Price | B8: ='Calculator'!$B$5
A9: Gap Size | B9: =IF(AND(B8>0,B7>0),MAX(1,CEILING(B8*'Calculator'!$B$6/100*0.5/B7,1))*B7,0)
A10: Min Sell Price | B10: =IF(AND(B8>0,B9>0),B8+B9,0)
A12: Buy Order Totals
A13: Total Buy Qty | B13: =SUM('Calculator'!G35:G54)
A14: Total Cost | B14: =SUM('Calculator'!F35:F54)
A15: Target Revenue | B15: =B14*(1+'Calculator'!$B$6/100)
A17: Sell Order Helpers
A18: Initial Revenue | B18: =SUMPRODUCT('Calculator'!B60:B79,'Calculator'!G60:G79)
A19: Price Scale | B19: =IF(AND(B18>0,'Helpers'!$B$15>0),'Helpers'!$B$15/B18,1)
A20: Min Valid Sell | B20: =IF(AND('Helpers'!$B$8>0,'Helpers'!$B$7>0),'Helpers'!$B$8+'Helpers'!$B$7,0)
A22: Validation Checks
A23: Budget > 0 | B23: =IF('Calculator'!$B$4>0,"✓ OK","✗ ERROR: Budget must be positive")
A24: Current Price > 0 | B24: =IF('Calculator'!$B$5>0,"✓ OK","✗ ERROR: Price must be positive")
A25: Profit Target Valid | B25: =IF(AND('Calculator'!$B$6>=10,'Calculator'!$B$6<=200),"✓ OK","✗ ERROR: Profit target must be 10-200%")
A26: Num Rungs >= 1 | B26: =IF('Calculator'!$B$7>=1,"✓ OK","✗ ERROR: Number of rungs must be at least 1")
A27: Buy Price Range Valid | B27: =IF(AND('Calculator'!$B$8>0,'Calculator'!$B$8<=100),"✓ OK","✗ ERROR: Buy price range must be 0-100%")
A28: Buy Lower > 0 | B28: =IF('Helpers'!$B$6>0,"✓ OK","✗ ERROR: Buy lower price is non-positive. Reduce Buy Price Range %")
A29: Sell Prices > Buy Prices | B29: =IF(AND('Calculator'!$B$7>0,'Calculator'!$B$7<=20,SUM('Calculator'!B35:B54)>0,SUM('Calculator'!C60:C79)>0),IF(AND(ISNUMBER(INDEX('Calculator'!C60:C79,1)),ISNUMBER(INDEX('Calculator'!B35:B54,'Calculator'!$B$7))),IF(INDEX('Calculator'!C60:C79,1)>INDEX('Calculator'!B35:B54,'Calculator'!$B$7),"✓ OK","✗ ERROR: Sell prices must exceed buy prices"),"N/A"),"N/A")
A30: Volume Match | B30: =IF(ABS('Helpers'!$B$13-SUM('Calculator'!G60:G79))<0.0001,"✓ OK","⚠ WARNING: Buy and sell quantities do not match exactly")

Sheet Charts
