Workbook

Sheet Calculator
A1: STAGGERED ORDER LADDER CALCULATOR
A3: INPUT PARAMETERS
A4: Total Budget ($) | B4: 10000 | C4: Total amount available for buy orders
A5: Current Price ($) | B5: 50 | C5: Current market price (highest buy rung)
A6: Profit Target (%) | B6: 75 | C6: Target profit percentage (10-200%)
A7: Number of Rungs | B7: 10 | C7: Number of buy/sell orders to place
A8: Buy Price Range (%) | B8: 30 | C8: Price range for buy ladder (0-100%)
A10: SUMMARY RESULTS
A11: Total Budget | B11: =$B$4 -> 10000
A12: Number of Rungs | B12: =$B$7 -> 10
A13: Total Cost | B13: =SUM(F21:F40) -> 10000
A14: Total Revenue | B14: =SUM(H46:H65) -> 17500
A15: Total Profit | B15: =B14-B13 -> 7500
A16: Profit Percentage | B16: =IF(B13>0,(B15/B13)*100,0) -> 75
A17: Total Buy Quantity | B17: =SUM(G21:G40) -> 254.81114
A18: Total Sell Quantity | B18: =SUM(G46:G65) -> 254.81114
A20: BUY ORDERS
A21: 1 | B21: =IF(1<=$B$7,Helpers!$B$6+(Helpers!$B$5-Helpers!$B$6)*(1-1)/(IF($B$7>1,$B$7-1,1)),0) -> 35 | C21: =IF(1<=$B$7,EXP(2-2*(1-1)/(IF($B$7>1,$B$7-1,1))),0) -> 7.3890561 | D21: =IF(1<=$B$7,IF(SUM(C21:C40)>0,C21/SUM(C21:C40),0),0) -> 0.22348077 | E21: =IF(1<=$B$7,IF(ISNUMBER(D21),$B$4*D21,0),0) -> 2234.8077 | F21: =IF(1<=$B$7,IF(AND(ISNUMBER(E21),SUM(E21:E40)>0),E21*($B$4/SUM(E21:E40)),0),0) -> 2234.8077 | G21: =IF(1<=$B$7,IF(B21>0,F21/B21,0),0) -> 63.851647 | H21: =F21 -> 2234.8077 | I21: =G21 -> 63.851647 | J21: =IF(1<=$B$7,IF(I21>0,H21/I21,0),0) -> 35 | K21: =IF(AND(A21<=$B$7,B21>0,G21>0,ISNUMBER(B21),ISNUMBER(G21)),"Yes","No") -> Yes
A22: 2 | B22: =IF(2<=$B$7,Helpers!$B$6+(Helpers!$B$5-Helpers!$B$6)*(2-1)/(IF($B$7>1,$B$7-1,1)),0) -> 36.666667 | C22: =IF(2<=$B$7,EXP(2-2*(2-1)/(IF($B$7>1,$B$7-1,1))),0) -> 5.9166936 | D22: =IF(2<=$B$7,IF(SUM(C21:C40)>0,C22/SUM(C21:C40),0),0) -> 0.17894941 | E22: =IF(2<=$B$7,IF(ISNUMBER(D22),$B$4*D22,0),0) -> 1789.4941 | F22: =IF(2<=$B$7,IF(AND(ISNUMBER(E22),SUM(E21:E40)>0),E22*($B$4/SUM(E21:E40)),0),0) -> 1789.4941 | G22: =IF(2<=$B$7,IF(B22>0,F22/B22,0),0) -> 48.804384 | H22: =IF(2<=$B$7,F22+H21,0) -> 4024.3017 | I22: =IF(2<=$B$7,G22+I21,0) -> 112.65603 | J22: =IF(2<=$B$7,IF(I22>0,H22/I22,0),0) -> 35.722026 | K22: =IF(AND(A22<=$B$7,B22>0,G22>0,ISNUMBER(B22),ISNUMBER(G22)),"Yes","No") -> Yes
A23: 3 | B23: =IF(3<=$B$7,Helpers!$B$6+(Helpers!$B$5-Helpers!$B$6)*(3-1)/(IF($B$7>1,$B$7-1,1)),0) -> 38.333333 | C23: =IF(3<=$B$7,EXP(2-2*(3-1)/(IF($B$7>1,$B$7-1,1))),0) -> 4.7377179 | D23: =IF(3<=$B$7,IF(SUM(C21:C40)>0,C23/SUM(C21:C40),0),0) -> 0.14329148 | E23: =IF(3<=$B$7,IF(ISNUMBER(D23),$B$4*D23,0),0) -> 1432.9148 | F23: =IF(3<=$B$7,IF(AND(ISNUMBER(E23),SUM(E21:E40)>0),E23*($B$4/SUM(E21:E40)),0),0) -> 1432.9148 | G23: =IF(3<=$B$7,IF(B23>0,F23/B23,0),0) -> 37.380387 | H23: =IF(3<=$B$7,F23+H22,0) -> 5457.2166 | I23: =IF(3<=$B$7,G23+I22,0) -> 150.03642 | J23: =IF(3<=$B$7,IF(I23>0,H23/I23,0),0) -> 36.372613 | K23: =IF(AND(A23<=$B$7,B23>0,G23>0,ISNUMBER(B23),ISNUMBER(G23)),"Yes","No") -> Yes
A24: 4 | B24: =IF(4<=$B$7,Helpers!$B$6+(Helpers!$B$5-Helpers!$B$6)*(4-1)/(IF($B$7>1,$B$7-1,1)),0) -> 40 | C24: =IF(4<=$B$7,EXP(2-2*(4-1)/(IF($B$7>1,$B$7-1,1))),0) -> 3.7936679 | D24: =IF(4<=$B$7,IF(SUM(C21:C40)>0,C24/SUM(C21:C40),0),0) -> 0.11473885 | E24: =IF(4<=$B$7,IF(ISNUMBER(D24),$B$4*D24,0),0) -> 1147.3885 | F24: =IF(4<=$B$7,IF(AND(ISNUMBER(E24),SUM(E21:E40)>0),E24*($B$4/SUM(E21:E40)),0),0) -> 1147.3885 | G24: =IF(4<=$B$7,IF(B24>0,F24/B24,0),0) -> 28.684713 | H24: =IF(4<=$B$7,F24+H23,0) -> 6604.6051 | I24: =IF(4<=$B$7,G24+I23,0) -> 178.72113 | J24: =IF(4<=$B$7,IF(I24>0,H24/I24,0),0) -> 36.954808 | K24: =IF(AND(A24<=$B$7,B24>0,G24>0,ISNUMBER(B24),ISNUMBER(G24)),"Yes","No") -> Yes
A25: 5 | B25: =IF(5<=$B$7,Helpers!$B$6+(Helpers!$B$5-Helpers!$B$6)*(5-1)/(IF($B$7>1,$B$7-1,1)),0) -> 41.666667 | C25: =IF(5<=$B$7,EXP(2-2*(5-1)/(IF($B$7>1,$B$7-1,1))),0) -> 3.0377318 | D25: =IF(5<=$B$7,IF(SUM(C21:C40)>0,C25/SUM(C21:C40),0),0) -> 0.09187569 | E25: =IF(5<=$B$7,IF(ISNUMBER(D25),$B$4*D25,0),0) -> 918.7569 | F25: =IF(5<=$B$7,IF(AND(ISNUMBER(E25),SUM(E21:E40)>0),E25*($B$4/SUM(E21:E40)),0),0) -> 918.7569 | G25: =IF(5<=$B$7,IF(B25>0,F25/B25,0),0) -> 22.050165 | H25: =IF(5<=$B$7,F25+H24,0) -> 7523.362 | I25: =IF(5<=$B$7,G25+I24,0) -> 200.7713 | J25: =IF(5<=$B$7,IF(I25>0,H25/I25,0),0) -> 37.472299 | K25: =IF(AND(A25<=$B$7,B25>0,G25>0,ISNUMBER(B25),ISNUMBER(G25)),"Yes","No") -> Yes
A26: 6 | B26: =IF(6<=$B$7,Helpers!$B$6+(Helpers!$B$5-Helpers!$B$6)*(6-1)/(IF($B$7>1,$B$7-1,1)),0) -> 43.333333 | C26: =IF(6<=$B$7,EXP(2-2*(6-1)/(IF($B$7>1,$B$7-1,1))),0) -> 2.4324255 | D26: =IF(6<=$B$7,IF(SUM(C21:C40)>0,C26/SUM(C21:C40),0),0) -> 0.073568301 | E26: =IF(6<=$B$7,IF(ISNUMBER(D26),$B$4*D26,0),0) -> 735.68301 | F26: =IF(6<=$B$7,IF(AND(ISNUMBER(E26),SUM(E21:E40)>0),E26*($B$4/SUM(E21:E40)),0),0) -> 735.68301 | G26: =IF(6<=$B$7,IF(B26>0,F26/B26,0),0) -> 16.9773 | H26: =IF(6<=$B$7,F26+H25,0) -> 8259.045 | I26: =IF(6<=$B$7,G26+I25,0) -> 217.7486 | J26: =IF(6<=$B$7,IF(I26>0,H26/I26,0),0) -> 37.929268 | K26: =IF(AND(A26<=$B$7,B26>0,G26>0,ISNUMBER(B26),ISNUMBER(G26)),"Yes","No") -> Yes
A27: 7 | B27: =IF(7<=$B$7,Helpers!$B$6+(Helpers!$B$5-Helpers!$B$6)*(7-1)/(IF($B$7>1,$B$7-1,1)),0) -> 45 | C27: =IF(7<=$B$7,EXP(2-2*(7-1)/(IF($B$7>1,$B$7-1,1))),0) -> 1.947734 | D27: =IF(7<=$B$7,IF(SUM(C21:C40)>0,C27/SUM(C21:C40),0),0) -> 0.05890889 | E27: =IF(7<=$B$7,IF(ISNUMBER(D27),$B$4*D27,0),0) -> 589.0889 | F27: =IF(7<=$B$7,IF(AND(ISNUMBER(E27),SUM(E21:E40)>0),E27*($B$4/SUM(E21:E40)),0),0) -> 589.0889 | G27: =IF(7<=$B$7,IF(B27>0,F27/B27,0),0) -> 13.090865 | H27: =IF(7<=$B$7,F27+H26,0) -> 8848.1339 | I27: =IF(7<=$B$7,G27+I26,0) -> 230.83946 | J27: =IF(7<=$B$7,IF(I27>0,H27/I27,0),0) -> 38.330248 | K27: =IF(AND(A27<=$B$7,B27>0,G27>0,ISNUMBER(B27),ISNUMBER(G27)),"Yes","No") -> Yes
A28: 8 | B28: =IF(8<=$B$7,Helpers!$B$6+(Helpers!$B$5-Helpers!$B$6)*(8-1)/(IF($B$7>1,$B$7-1,1)),0) -> 46.666667 | C28: =IF(8<=$B$7,EXP(2-2*(8-1)/(IF($B$7>1,$B$7-1,1))),0) -> 1.5596235 | D28: =IF(8<=$B$7,IF(SUM(C21:C40)>0,C28/SUM(C21:C40),0),0) -> 0.047170552 | E28: =IF(8<=$B$7,IF(ISNUMBER(D28),$B$4*D28,0),0) -> 471.70552 | F28: =IF(8<=$B$7,IF(AND(ISNUMBER(E28),SUM(E21:E40)>0),E28*($B$4/SUM(E21:E40)),0),0) -> 471.70552 | G28: =IF(8<=$B$7,IF(B28>0,F28/B28,0),0) -> 10.107975 | H28: =IF(8<=$B$7,F28+H27,0) -> 9319.8394 | I28: =IF(8<=$B$7,G28+I27,0) -> 240.94744 | J28: =IF(8<=$B$7,IF(I28>0,H28/I28,0),0) -> 38.679969 | K28: =IF(AND(A28<=$B$7,B28>0,G28>0,ISNUMBER(B28),ISNUMBER(G28)),"Yes","No") -> Yes
A29: 9 | B29: =IF(9<=$B$7,Helpers!$B$6+(Helpers!$B$5-Helpers!$B$6)*(9-1)/(IF($B$7>1,$B$7-1,1)),0) -> 48.333333 | C29: =IF(9<=$B$7,EXP(2-2*(9-1)/(IF($B$7>1,$B$7-1,1))),0) -> 1.2488489 | D29: =IF(9<=$B$7,IF(SUM(C21:C40)>0,C29/SUM(C21:C40),0),0) -> 0.037771225 | E29: =IF(9<=$B$7,IF(ISNUMBER(D29),$B$4*D29,0),0) -> 377.71225 | F29: =IF(9<=$B$7,IF(AND(ISNUMBER(E29),SUM(E21:E40)>0),E29*($B$4/SUM(E21:E40)),0),0) -> 377.71225 | G29: =IF(9<=$B$7,IF(B29>0,F29/B29,0),0) -> 7.8147362 | H29: =IF(9<=$B$7,F29+H28,0) -> 9697.5517 | I29: =IF(9<=$B$7,G29+I28,0) -> 248.76217 | J29: =IF(9<=$B$7,IF(I29>0,H29/I29,0),0) -> 38.983225 | K29: =IF(AND(A29<=$B$7,B29>0,G29>0,ISNUMBER(B29),ISNUMBER(G29)),"Yes","No") -> Yes
A30: 10 | B30: =IF(10<=$B$7,Helpers!$B$6+(Helpers!$B$5-Helpers!$B$6)*(10-1)/(IF($B$7>1,$B$7-1,1)),0) -> 50 | C30: =IF(10<=$B$7,EXP(2-2*(10-1)/(IF($B$7>1,$B$7-1,1))),0) -> 1 | D30: =IF(10<=$B$7,IF(SUM(C21:C40)>0,C30/SUM(C21:C40),0),0) -> 0.030244833 | E30: =IF(10<=$B$7,IF(ISNUMBER(D30),$B$4*D30,0),0) -> 302.44833 | F30: =IF(10<=$B$7,IF(AND(ISNUMBER(E30),SUM(E21:E40)>0),E30*($B$4/SUM(E21:E40)),0),0) -> 302.44833 | G30: =IF(10<=$B$7,IF(B30>0,F30/B30,0),0) -> 6.0489666 | H30: =IF(10<=$B$7,F30+H29,0) -> 10000 | I30: =IF(10<=$B$7,G30+I29,0) -> 254.81114 | J30: =IF(10<=$B$7,IF(I30>0,H30/I30,0),0) -> 39.244752 | K30: =IF(AND(A30<=$B$7,B30>0,G30>0,ISNUMBER(B30),ISNUMBER(G30)),"Yes","No") -> Yes
A31: 11 | B31: =IF(11<=$B$7,Helpers!$B$6+(Helpers!$B$5-Helpers!$B$6)*(11-1)/(IF($B$7>1,$B$7-1,1)),0) -> 0 | C31: =IF(11<=$B$7,EXP(2-2*(11-1)/(IF($B$7>1,$B$7-1,1))),0) -> 0 | D31: =IF(11<=$B$7,IF(SUM(C21:C40)>0,C31/SUM(C21:C40),0),0) -> 0 | E31: =IF(11<=$B$7,IF(ISNUMBER(D31),$B$4*D31,0),0) -> 0 | F31: =IF(11<=$B$7,IF(AND(ISNUMBER(E31),SUM(E21:E40)>0),E31*($B$4/SUM(E21:E40)),0),0) -> 0 | G31: =IF(11<=$B$7,IF(B31>0,F31/B31,0),0) -> 0 | H31: =IF(11<=$B$7,F31+H30,0) -> 0 | I31: =IF(11<=$B$7,G31+I30,0) -> 0 | J31: =IF(11<=$B$7,IF(I31>0,H31/I31,0),0) -> 0 | K31: =IF(AND(A31<=$B$7,B31>0,G31>0,ISNUMBER(B31),ISNUMBER(G31)),"Yes","No") -> No
A32: 12 | B32: =IF(12<=$B$7,Helpers!$B$6+(Helpers!$B$5-Helpers!$B$6)*(12-1)/(IF($B$7>1,$B$7-1,1)),0) -> 0 | C32: =IF(12<=$B$7,EXP(2-2*(12-1)/(IF($B$7>1,$B$7-1,1))),0) -> 0 | D32: =IF(12<=$B$7,IF(SUM(C21:C40)>0,C32/SUM(C21:C40),0),0) -> 0 | E32: =IF(12<=$B$7,IF(ISNUMBER(D32),$B$4*D32,0),0) -> 0 | F32: =IF(12<=$B$7,IF(AND(ISNUMBER(E32),SUM(E21:E40)>0),E32*($B$4/SUM(E21:E40)),0),0) -> 0 | G32: =IF(12<=$B$7,IF(B32>0,F32/B32,0),0) -> 0 | H32: =IF(12<=$B$7,F32+H31,0) -> 0 | I32: =IF(12<=$B$7,G32+I31,0) -> 0 | J32: =IF(12<=$B$7,IF(I32>0,H32/I32,0),0) -> 0 | K32: =IF(AND(A32<=$B$7,B32>0,G32>0,ISNUMBER(B32),ISNUMBER(G32)),"Yes","No") -> No
A33: 13 | B33: =IF(13<=$B$7,Helpers!$B$6+(Helpers!$B$5-Helpers!$B$6)*(13-1)/(IF($B$7>1,$B$7-1,1)),0) -> 0 | C33: =IF(13<=$B$7,EXP(2-2*(13-1)/(IF($B$7>1,$B$7-1,1))),0) -> 0 | D33: =IF(13<=$B$7,IF(SUM(C21:C40)>0,C33/SUM(C21:C40),0),0) -> 0 | E33: =IF(13<=$B$7,IF(ISNUMBER(D33),$B$4*D33,0),0) -> 0 | F33: =IF(13<=$B$7,IF(AND(ISNUMBER(E33),SUM(E21:E40)>0),E33*($B$4/SUM(E21:E40)),0),0) -> 0 | G33: =IF(13<=$B$7,IF(B33>0,F33/B33,0),0) -> 0 | H33: =IF(13<=$B$7,F33+H32,0) -> 0 | I33: =IF(13<=$B$7,G33+I32,0) -> 0 | J33: =IF(13<=$B$7,IF(I33>0,H33/I33,0),0) -> 0 | K33: =IF(AND(A33<=$B$7,B33>0,G33>0,ISNUMBER(B33),ISNUMBER(G33)),"Yes","No") -> No
A34: 14 | B34: =IF(14<=$B$7,Helpers!$B$6+(Helpers!$B$5-Helpers!$B$6)*(14-1)/(IF($B$7>1,$B$7-1,1)),0) -> 0 | C34: =IF(14<=$B$7,EXP(2-2*(14-1)/(IF($B$7>1,$B$7-1,1))),0) -> 0 | D34: =IF(14<=$B$7,IF(SUM(C21:C40)>0,C34/SUM(C21:C40),0),0) -> 0 | E34: =IF(14<=$B$7,IF(ISNUMBER(D34),$B$4*D34,0),0) -> 0 | F34: =IF(14<=$B$7,IF(AND(ISNUMBER(E34),SUM(E21:E40)>0),E34*($B$4/SUM(E21:E40)),0),0) -> 0 | G34: =IF(14<=$B$7,IF(B34>0,F34/B34,0),0) -> 0 | H34: =IF(14<=$B$7,F34+H33,0) -> 0 | I34: =IF(14<=$B$7,G34+I33,0) -> 0 | J34: =IF(14<=$B$7,IF(I34>0,H34/I34,0),0) -> 0 | K34: =IF(AND(A34<=$B$7,B34>0,G34>0,ISNUMBER(B34),ISNUMBER(G34)),"Yes","No") -> No
A35: 15 | B35: =IF(15<=$B$7,Helpers!$B$6+(Helpers!$B$5-Helpers!$B$6)*(15-1)/(IF($B$7>1,$B$7-1,1)),0) -> 0 | C35: =IF(15<=$B$7,EXP(2-2*(15-1)/(IF($B$7>1,$B$7-1,1))),0) -> 0 | D35: =IF(15<=$B$7,IF(SUM(C21:C40)>0,C35/SUM(C21:C40),0),0) -> 0 | E35: =IF(15<=$B$7,IF(ISNUMBER(D35),$B$4*D35,0),0) -> 0 | F35: =IF(15<=$B$7,IF(AND(ISNUMBER(E35),SUM(E21:E40)>0),E35*($B$4/SUM(E21:E40)),0),0) -> 0 | G35: =IF(15<=$B$7,IF(B35>0,F35/B35,0),0) -> 0 | H35: =IF(15<=$B$7,F35+H34,0) -> 0 | I35: =IF(15<=$B$7,G35+I34,0) -> 0 | J35: =IF(15<=$B$7,IF(I35>0,H35/I35,0),0) -> 0 | K35: =IF(AND(A35<=$B$7,B35>0,G35>0,ISNUMBER(B35),ISNUMBER(G35)),"Yes","No") -> No
A36: 16 | B36: =IF(16<=$B$7,Helpers!$B$6+(Helpers!$B$5-Helpers!$B$6)*(16-1)/(IF($B$7>1,$B$7-1,1)),0) -> 0 | C36: =IF(16<=$B$7,EXP(2-2*(16-1)/(IF($B$7>1,$B$7-1,1))),0) -> 0 | D36: =IF(16<=$B$7,IF(SUM(C21:C40)>0,C36/SUM(C21:C40),0),0) -> 0 | E36: =IF(16<=$B$7,IF(ISNUMBER(D36),$B$4*D36,0),0) -> 0 | F36: =IF(16<=$B$7,IF(AND(ISNUMBER(E36),SUM(E21:E40)>0),E36*($B$4/SUM(E21:E40)),0),0) -> 0 | G36: =IF(16<=$B$7,IF(B36>0,F36/B36,0),0) -> 0 | H36: =IF(16<=$B$7,F36+H35,0) -> 0 | I36: =IF(16<=$B$7,G36+I35,0) -> 0 | J36: =IF(16<=$B$7,IF(I36>0,H36/I36,0),0) -> 0 | K36: =IF(AND(A36<=$B$7,B36>0,G36>0,ISNUMBER(B36),ISNUMBER(G36)),"Yes","No") -> No
A37: 17 | B37: =IF(17<=$B$7,Helpers!$B$6+(Helpers!$B$5-Helpers!$B$6)*(17-1)/(IF($B$7>1,$B$7-1,1)),0) -> 0 | C37: =IF(17<=$B$7,EXP(2-2*(17-1)/(IF($B$7>1,$B$7-1,1))),0) -> 0 | D37: =IF(17<=$B$7,IF(SUM(C21:C40)>0,C37/SUM(C21:C40),0),0) -> 0 | E37: =IF(17<=$B$7,IF(ISNUMBER(D37),$B$4*D37,0),0) -> 0 | F37: =IF(17<=$B$7,IF(AND(ISNUMBER(E37),SUM(E21:E40)>0),E37*($B$4/SUM(E21:E40)),0),0) -> 0 | G37: =IF(17<=$B$7,IF(B37>0,F37/B37,0),0) -> 0 | H37: =IF(17<=$B$7,F37+H36,0) -> 0 | I37: =IF(17<=$B$7,G37+I36,0) -> 0 | J37: =IF(17<=$B$7,IF(I37>0,H37/I37,0),0) -> 0 | K37: =IF(AND(A37<=$B$7,B37>0,G37>0,ISNUMBER(B37),ISNUMBER(G37)),"Yes","No") -> No
A38: 18 | B38: =IF(18<=$B$7,Helpers!$B$6+(Helpers!$B$5-Helpers!$B$6)*(18-1)/(IF($B$7>1,$B$7-1,1)),0) -> 0 | C38: =IF(18<=$B$7,EXP(2-2*(18-1)/(IF($B$7>1,$B$7-1,1))),0) -> 0 | D38: =IF(18<=$B$7,IF(SUM(C21:C40)>0,C38/SUM(C21:C40),0),0) -> 0 | E38: =IF(18<=$B$7,IF(ISNUMBER(D38),$B$4*D38,0),0) -> 0 | F38: =IF(18<=$B$7,IF(AND(ISNUMBER(E38),SUM(E21:E40)>0),E38*($B$4/SUM(E21:E40)),0),0) -> 0 | G38: =IF(18<=$B$7,IF(B38>0,F38/B38,0),0) -> 0 | H38: =IF(18<=$B$7,F38+H37,0) -> 0 | I38: =IF(18<=$B$7,G38+I37,0) -> 0 | J38: =IF(18<=$B$7,IF(I38>0,H38/I38,0),0) -> 0 | K38: =IF(AND(A38<=$B$7,B38>0,G38>0,ISNUMBER(B38),ISNUMBER(G38)),"Yes","No") -> No
A39: 19 | B39: =IF(19<=$B$7,Helpers!$B$6+(Helpers!$B$5-Helpers!$B$6)*(19-1)/(IF($B$7>1,$B$7-1,1)),0) -> 0 | C39: =IF(19<=$B$7,EXP(2-2*(19-1)/(IF($B$7>1,$B$7-1,1))),0) -> 0 | D39: =IF(19<=$B$7,IF(SUM(C21:C40)>0,C39/SUM(C21:C40),0),0) -> 0 | E39: =IF(19<=$B$7,IF(ISNUMBER(D39),$B$4*D39,0),0) -> 0 | F39: =IF(19<=$B$7,IF(AND(ISNUMBER(E39),SUM(E21:E40)>0),E39*($B$4/SUM(E21:E40)),0),0) -> 0 | G39: =IF(19<=$B$7,IF(B39>0,F39/B39,0),0) -> 0 | H39: =IF(19<=$B$7,F39+H38,0) -> 0 | I39: =IF(19<=$B$7,G39+I38,0) -> 0 | J39: =IF(19<=$B$7,IF(I39>0,H39/I39,0),0) -> 0 | K39: =IF(AND(A39<=$B$7,B39>0,G39>0,ISNUMBER(B39),ISNUMBER(G39)),"Yes","No") -> No
A40: 20 | B40: =IF(20<=$B$7,Helpers!$B$6+(Helpers!$B$5-Helpers!$B$6)*(20-1)/(IF($B$7>1,$B$7-1,1)),0) -> 0 | C40: =IF(20<=$B$7,EXP(2-2*(20-1)/(IF($B$7>1,$B$7-1,1))),0) -> 0 | D40: =IF(20<=$B$7,IF(SUM(C21:C40)>0,C40/SUM(C21:C40),0),0) -> 0 | E40: =IF(20<=$B$7,IF(ISNUMBER(D40),$B$4*D40,0),0) -> 0 | F40: =IF(20<=$B$7,IF(AND(ISNUMBER(E40),SUM(E21:E40)>0),E40*($B$4/SUM(E21:E40)),0),0) -> 0 | G40: =IF(20<=$B$7,IF(B40>0,F40/B40,0),0) -> 0 | H40: =IF(20<=$B$7,F40+H39,0) -> 0 | I40: =IF(20<=$B$7,G40+I39,0) -> 0 | J40: =IF(20<=$B$7,IF(I40>0,H40/I40,0),0) -> 0 | K40: =IF(AND(A40<=$B$7,B40>0,G40>0,ISNUMBER(B40),ISNUMBER(G40)),"Yes","No") -> No
A45: SELL ORDERS
A46: 1 | B46: =IF(1<=$B$7,Helpers!$B$10+Helpers!$B$7*(1-1),0) -> 70 | C46: =IF(1<=$B$7,MAX(B46*Helpers!$B$19,Helpers!$B$20+Helpers!$B$7*(1-1)),0) -> 59.848042 | D46: =IF(1<=$B$7,EXP(2*(1-1)/(IF($B$7>1,$B$7-1,1))),0) -> 1 | E46: =IF(1<=$B$7,IF(SUM(D46:D65)>0,D46/SUM(D46:D65),0),0) -> 0.030244833 | F46: =IF(1<=$B$7,Helpers!$B$13*E46,0) -> 7.7067203 | G46: =IF(1<=$B$7,IF(AND(ISNUMBER(F46),SUM(F46:F65)>0,Helpers!$B$13>0),F46*(Helpers!$B$13/SUM(F46:F65)),0),0) -> 7.7067203 | H46: =IF(1<=$B$7,C46*G46,0) -> 461.23212 | I46: =H46 -> 461.23212 | J46: =G46 -> 7.7067203 | K46: =IF(1<=$B$7,IF(J46>0,I46/J46,0),0) -> 59.848042 | L46: =IF(AND(A46<=$B$7,C46>0,G46>0,ISNUMBER(C46),ISNUMBER(G46)),"Yes","No") -> Yes
A47: 2 | B47: =IF(2<=$B$7,Helpers!$B$10+Helpers!$B$7*(2-1),0) -> 71.666667 | C47: =IF(2<=$B$7,MAX(B47*Helpers!$B$19,Helpers!$B$20+Helpers!$B$7*(2-1)),0) -> 61.272995 | D47: =IF(2<=$B$7,EXP(2*(2-1)/(IF($B$7>1,$B$7-1,1))),0) -> 1.2488489 | E47: =IF(2<=$B$7,IF(SUM(D46:D65)>0,D47/SUM(D46:D65),0),0) -> 0.037771225 | F47: =IF(2<=$B$7,Helpers!$B$13*E47,0) -> 9.6245289 | G47: =IF(2<=$B$7,IF(AND(ISNUMBER(F47),SUM(F46:F65)>0,Helpers!$B$13>0),F47*(Helpers!$B$13/SUM(F46:F65)),0),0) -> 9.6245289 | H47: =IF(2<=$B$7,C47*G47,0) -> 589.72372 | I47: =IF(2<=$B$7,H47+I46,0) -> 1050.9558 | J47: =IF(2<=$B$7,G47+J46,0) -> 17.331249 | K47: =IF(2<=$B$7,IF(J47>0,I47/J47,0),0) -> 60.639359 | L47: =IF(AND(A47<=$B$7,C47>0,G47>0,ISNUMBER(C47),ISNUMBER(G47)),"Yes","No") -> Yes
A48: 3 | B48: =IF(3<=$B$7,Helpers!$B$10+Helpers!$B$7*(3-1),0) -> 73.333333 | C48: =IF(3<=$B$7,MAX(B48*Helpers!$B$19,Helpers!$B$20+Helpers!$B$7*(3-1)),0) -> 62.697949 | D48: =IF(3<=$B$7,EXP(2*(3-1)/(IF($B$7>1,$B$7-1,1))),0) -> 1.5596235 | E48: =IF(3<=$B$7,IF(SUM(D46:D65)>0,D48/SUM(D46:D65),0),0) -> 0.047170552 | F48: =IF(3<=$B$7,Helpers!$B$13*E48,0) -> 12.019582 | G48: =IF(3<=$B$7,IF(AND(ISNUMBER(F48),SUM(F46:F65)>0,Helpers!$B$13>0),F48*(Helpers!$B$13/SUM(F46:F65)),0),0) -> 12.019582 | H48: =IF(3<=$B$7,C48*G48,0) -> 753.60314 | I48: =IF(3<=$B$7,H48+I47,0) -> 1804.559 | J48: =IF(3<=$B$7,G48+J47,0) -> 29.350831 | K48: =IF(3<=$B$7,IF(J48>0,I48/J48,0),0) -> 61.48238 | L48: =IF(AND(A48<=$B$7,C48>0,G48>0,ISNUMBER(C48),ISNUMBER(G48)),"Yes","No") -> Yes
A49: 4 | B49: =IF(4<=$B$7,Helpers!$B$10+Helpers!$B$7*(4-1),0) -> 75 | C49: =IF(4<=$B$7,MAX(B49*Helpers!$B$19,Helpers!$B$20+Helpers!$B$7*(4-1)),0) -> 64.122902 | D49: =IF(4<=$B$7,EXP(2*(4-1)/(IF($B$7>1,$B$7-1,1))),0) -> 1.947734 | E49: =IF(4<=$B$7,IF(SUM(D46:D65)>0,D49/SUM(D46:D65),0),0) -> 0.05890889 | F49: =IF(4<=$B$7,Helpers!$B$13*E49,0) -> 15.010641 | G49: =IF(4<=$B$7,IF(AND(ISNUMBER(F49),SUM(F46:F65)>0,Helpers!$B$13>0),F49*(Helpers!$B$13/SUM(F46:F65)),0),0) -> 15.010641 | H49: =IF(4<=$B$7,C49*G49,0) -> 962.52589 | I49: =IF(4<=$B$7,H49+I48,0) -> 2767.0849 | J49: =IF(4<=$B$7,G49+J48,0) -> 44.361473 | K49: =IF(4<=$B$7,IF(J49>0,I49/J49,0),0) -> 62.375857 | L49: =IF(AND(A49<=$B$7,C49>0,G49>0,ISNUMBER(C49),ISNUMBER(G49)),"Yes","No") -> Yes
A50: 5 | B50: =IF(5<=$B$7,Helpers!$B$10+Helpers!$B$7*(5-1),0) -> 76.666667 | C50: =IF(5<=$B$7,MAX(B50*Helpers!$B$19,Helpers!$B$20+Helpers!$B$7*(5-1)),0) -> 65.547856 | D50: =IF(5<=$B$7,EXP(2*(5-1)/(IF($B$7>1,$B$7-1,1))),0) -> 2.4324255 | E50: =IF(5<=$B$7,IF(SUM(D46:D65)>0,D50/SUM(D46:D65),0),0) -> 0.073568301 | F50: =IF(5<=$B$7,Helpers!$B$13*E50,0) -> 18.746023 | G50: =IF(5<=$B$7,IF(AND(ISNUMBER(F50),SUM(F46:F65)>0,Helpers!$B$13>0),F50*(Helpers!$B$13/SUM(F46:F65)),0),0) -> 18.746023 | H50: =IF(5<=$B$7,C50*G50,0) -> 1228.7616 | I50: =IF(5<=$B$7,H50+I49,0) -> 3995.8465 | J50: =IF(5<=$B$7,G50+J49,0) -> 63.107495 | K50: =IF(5<=$B$7,IF(J50>0,I50/J50,0),0) -> 63.318096 | L50: =IF(AND(A50<=$B$7,C50>0,G50>0,ISNUMBER(C50),ISNUMBER(G50)),"Yes","No") -> Yes
A51: 6 | B51: =IF(6<=$B$7,Helpers!$B$10+Helpers!$B$7*(6-1),0) -> 78.333333 | C51: =IF(6<=$B$7,MAX(B51*Helpers!$B$19,Helpers!$B$20+Helpers!$B$7*(6-1)),0) -> 66.972809 | D51: =IF(6<=$B$7,EXP(2*(6-1)/(IF($B$7>1,$B$7-1,1))),0) -> 3.0377318 | E51: =IF(6<=$B$7,IF(SUM(D46:D65)>0,D51/SUM(D46:D65),0),0) -> 0.09187569 | F51: =IF(6<=$B$7,Helpers!$B$13*E51,0) -> 23.410949 | G51: =IF(6<=$B$7,IF(AND(ISNUMBER(F51),SUM(F46:F65)>0,Helpers!$B$13>0),F51*(Helpers!$B$13/SUM(F46:F65)),0),0) -> 23.410949 | H51: =IF(6<=$B$7,C51*G51,0) -> 1567.897 | I51: =IF(6<=$B$7,H51+I50,0) -> 5563.7435 | J51: =IF(6<=$B$7,G51+J50,0) -> 86.518445 | K51: =IF(6<=$B$7,IF(J51>0,I51/J51,0),0) -> 64.307022 | L51: =IF(AND(A51<=$B$7,C51>0,G51>0,ISNUMBER(C51),ISNUMBER(G51)),"Yes","No") -> Yes
A52: 7 | B52: =IF(7<=$B$7,Helpers!$B$10+Helpers!$B$7*(7-1),0) -> 80 | C52: =IF(7<=$B$7,MAX(B52*Helpers!$B$19,Helpers!$B$20+Helpers!$B$7*(7-1)),0) -> 68.397762 | D52: =IF(7<=$B$7,EXP(2*(7-1)/(IF($B$7>1,$B$7-1,1))),0) -> 3.7936679 | E52: =IF(7<=$B$7,IF(SUM(D46:D65)>0,D52/SUM(D46:D65),0),0) -> 0.11473885 | F52: =IF(7<=$B$7,Helpers!$B$13*E52,0) -> 29.236737 | G52: =IF(7<=$B$7,IF(AND(ISNUMBER(F52),SUM(F46:F65)>0,Helpers!$B$13>0),F52*(Helpers!$B$13/SUM(F46:F65)),0),0) -> 29.236737 | H52: =IF(7<=$B$7,C52*G52,0) -> 1999.7274 | I52: =IF(7<=$B$7,H52+I51,0) -> 7563.4709 | J52: =IF(7<=$B$7,G52+J51,0) -> 115.75518 | K52: =IF(7<=$B$7,IF(J52>0,I52/J52,0),0) -> 65.340236 | L52: =IF(AND(A52<=$B$7,C52>0,G52>0,ISNUMBER(C52),ISNUMBER(G52)),"Yes","No") -> Yes
A53: 8 | B53: =IF(8<=$B$7,Helpers!$B$10+Helpers!$B$7*(8-1),0) -> 81.666667 | C53: =IF(8<=$B$7,MAX(B53*Helpers!$B$19,Helpers!$B$20+Helpers!$B$7*(8-1)),0) -> 69.822716 | D53: =IF(8<=$B$7,EXP(2*(8-1)/(IF($B$7>1,$B$7-1,1))),0) -> 4.7377179 | E53: =IF(8<=$B$7,IF(SUM(D46:D65)>0,D53/SUM(D46:D65),0),0) -> 0.14329148 | F53: =IF(8<=$B$7,Helpers!$B$13*E53,0) -> 36.512266 | G53: =IF(8<=$B$7,IF(AND(ISNUMBER(F53),SUM(F46:F65)>0,Helpers!$B$13>0),F53*(Helpers!$B$13/SUM(F46:F65)),0),0) -> 36.512266 | H53: =IF(8<=$B$7,C53*G53,0) -> 2549.3856 | I53: =IF(8<=$B$7,H53+I52,0) -> 10112.856 | J53: =IF(8<=$B$7,G53+J52,0) -> 152.26745 | K53: =IF(8<=$B$7,IF(J53>0,I53/J53,0),0) -> 66.415091 | L53: =IF(AND(A53<=$B$7,C53>0,G53>0,ISNUMBER(C53),ISNUMBER(G53)),"Yes","No") -> Yes
A54: 9 | B54: =IF(9<=$B$7,Helpers!$B$10+Helpers!$B$7*(9-1),0) -> 83.333333 | C54: =IF(9<=$B$7,MAX(B54*Helpers!$B$19,Helpers!$B$20+Helpers!$B$7*(9-1)),0) -> 71.247669 | D54: =IF(9<=$B$7,EXP(2*(9-1)/(IF($B$7>1,$B$7-1,1))),0) -> 5.9166936 | E54: =IF(9<=$B$7,IF(SUM(D46:D65)>0,D54/SUM(D46:D65),0),0) -> 0.17894941 | F54: =IF(9<=$B$7,Helpers!$B$13*E54,0) -> 45.598303 | G54: =IF(9<=$B$7,IF(AND(ISNUMBER(F54),SUM(F46:F65)>0,Helpers!$B$13>0),F54*(Helpers!$B$13/SUM(F46:F65)),0),0) -> 45.598303 | H54: =IF(9<=$B$7,C54*G54,0) -> 3248.7728 | I54: =IF(9<=$B$7,H54+I53,0) -> 13361.629 | J54: =IF(9<=$B$7,G54+J53,0) -> 197.86575 | K54: =IF(9<=$B$7,IF(J54>0,I54/J54,0),0) -> 67.528762 | L54: =IF(AND(A54<=$B$7,C54>0,G54>0,ISNUMBER(C54),ISNUMBER(G54)),"Yes","No") -> Yes
A55: 10 | B55: =IF(10<=$B$7,Helpers!$B$10+Helpers!$B$7*(10-1),0) -> 85 | C55: =IF(10<=$B$7,MAX(B55*Helpers!$B$19,Helpers!$B$20+Helpers!$B$7*(10-1)),0) -> 72.672622 | D55: =IF(10<=$B$7,EXP(2*(10-1)/(IF($B$7>1,$B$7-1,1))),0) -> 7.3890561 | E55: =IF(10<=$B$7,IF(SUM(D46:D65)>0,D55/SUM(D46:D65),0),0) -> 0.22348077 | F55: =IF(10<=$B$7,Helpers!$B$13*E55,0) -> 56.945389 | G55: =IF(10<=$B$7,IF(AND(ISNUMBER(F55),SUM(F46:F65)>0,Helpers!$B$13>0),F55*(Helpers!$B$13/SUM(F46:F65)),0),0) -> 56.945389 | H55: =IF(10<=$B$7,C55*G55,0) -> 4138.3707 | I55: =IF(10<=$B$7,H55+I54,0) -> 17500 | J55: =IF(10<=$B$7,G55+J54,0) -> 254.81114 | K55: =IF(10<=$B$7,IF(J55>0,I55/J55,0),0) -> 68.678316 | L55: =IF(AND(A55<=$B$7,C55>0,G55>0,ISNUMBER(C55),ISNUMBER(G55)),"Yes","No") -> Yes
A56: 11 | B56: =IF(11<=$B$7,Helpers!$B$10+Helpers!$B$7*(11-1),0) -> 0 | C56: =IF(11<=$B$7,MAX(B56*Helpers!$B$19,Helpers!$B$20+Helpers!$B$7*(11-1)),0) -> 0 | D56: =IF(11<=$B$7,EXP(2*(11-1)/(IF($B$7>1,$B$7-1,1))),0) -> 0 | E56: =IF(11<=$B$7,IF(SUM(D46:D65)>0,D56/SUM(D46:D65),0),0) -> 0 | F56: =IF(11<=$B$7,Helpers!$B$13*E56,0) -> 0 | G56: =IF(11<=$B$7,IF(AND(ISNUMBER(F56),SUM(F46:F65)>0,Helpers!$B$13>0),F56*(Helpers!$B$13/SUM(F46:F65)),0),0) -> 0 | H56: =IF(11<=$B$7,C56*G56,0) -> 0 | I56: =IF(11<=$B$7,H56+I55,0) -> 0 | J56: =IF(11<=$B$7,G56+J55,0) -> 0 | K56: =IF(11<=$B$7,IF(J56>0,I56/J56,0),0) -> 0 | L56: =IF(AND(A56<=$B$7,C56>0,G56>0,ISNUMBER(C56),ISNUMBER(G56)),"Yes","No") -> No
A57: 12 | B57: =IF(12<=$B$7,Helpers!$B$10+Helpers!$B$7*(12-1),0) -> 0 | C57: =IF(12<=$B$7,MAX(B57*Helpers!$B$19,Helpers!$B$20+Helpers!$B$7*(12-1)),0) -> 0 | D57: =IF(12<=$B$7,EXP(2*(12-1)/(IF($B$7>1,$B$7-1,1))),0) -> 0 | E57: =IF(12<=$B$7,IF(SUM(D46:D65)>0,D57/SUM(D46:D65),0),0) -> 0 | F57: =IF(12<=$B$7,Helpers!$B$13*E57,0) -> 0 | G57: =IF(12<=$B$7,IF(AND(ISNUMBER(F57),SUM(F46:F65)>0,Helpers!$B$13>0),F57*(Helpers!$B$13/SUM(F46:F65)),0),0) -> 0 | H57: =IF(12<=$B$7,C57*G57,0) -> 0 | I57: =IF(12<=$B$7,H57+I56,0) -> 0 | J57: =IF(12<=$B$7,G57+J56,0) -> 0 | K57: =IF(12<=$B$7,IF(J57>0,I57/J57,0),0) -> 0 | L57: =IF(AND(A57<=$B$7,C57>0,G57>0,ISNUMBER(C57),ISNUMBER(G57)),"Yes","No") -> No
A58: 13 | B58: =IF(13<=$B$7,Helpers!$B$10+Helpers!$B$7*(13-1),0) -> 0 | C58: =IF(13<=$B$7,MAX(B58*Helpers!$B$19,Helpers!$B$20+Helpers!$B$7*(13-1)),0) -> 0 | D58: =IF(13<=$B$7,EXP(2*(13-1)/(IF($B$7>1,$B$7-1,1))),0) -> 0 | E58: =IF(13<=$B$7,IF(SUM(D46:D65)>0,D58/SUM(D46:D65),0),0) -> 0 | F58: =IF(13<=$B$7,Helpers!$B$13*E58,0) -> 0 | G58: =IF(13<=$B$7,IF(AND(ISNUMBER(F58),SUM(F46:F65)>0,Helpers!$B$13>0),F58*(Helpers!$B$13/SUM(F46:F65)),0),0) -> 0 | H58: =IF(13<=$B$7,C58*G58,0) -> 0 | I58: =IF(13<=$B$7,H58+I57,0) -> 0 | J58: =IF(13<=$B$7,G58+J57,0) -> 0 | K58: =IF(13<=$B$7,IF(J58>0,I58/J58,0),0) -> 0 | L58: =IF(AND(A58<=$B$7,C58>0,G58>0,ISNUMBER(C58),ISNUMBER(G58)),"Yes","No") -> No
A59: 14 | B59: =IF(14<=$B$7,Helpers!$B$10+Helpers!$B$7*(14-1),0) -> 0 | C59: =IF(14<=$B$7,MAX(B59*Helpers!$B$19,Helpers!$B$20+Helpers!$B$7*(14-1)),0) -> 0 | D59: =IF(14<=$B$7,EXP(2*(14-1)/(IF($B$7>1,$B$7-1,1))),0) -> 0 | E59: =IF(14<=$B$7,IF(SUM(D46:D65)>0,D59/SUM(D46:D65),0),0) -> 0 | F59: =IF(14<=$B$7,Helpers!$B$13*E59,0) -> 0 | G59: =IF(14<=$B$7,IF(AND(ISNUMBER(F59),SUM(F46:F65)>0,Helpers!$B$13>0),F59*(Helpers!$B$13/SUM(F46:F65)),0),0) -> 0 | H59: =IF(14<=$B$7,C59*G59,0) -> 0 | I59: =IF(14<=$B$7,H59+I58,0) -> 0 | J59: =IF(14<=$B$7,G59+J58,0) -> 0 | K59: =IF(14<=$B$7,IF(J59>0,I59/J59,0),0) -> 0 | L59: =IF(AND(A59<=$B$7,C59>0,G59>0,ISNUMBER(C59),ISNUMBER(G59)),"Yes","No") -> No
A60: 15 | B60: =IF(15<=$B$7,Helpers!$B$10+Helpers!$B$7*(15-1),0) -> 0 | C60: =IF(15<=$B$7,MAX(B60*Helpers!$B$19,Helpers!$B$20+Helpers!$B$7*(15-1)),0) -> 0 | D60: =IF(15<=$B$7,EXP(2*(15-1)/(IF($B$7>1,$B$7-1,1))),0) -> 0 | E60: =IF(15<=$B$7,IF(SUM(D46:D65)>0,D60/SUM(D46:D65),0),0) -> 0 | F60: =IF(15<=$B$7,Helpers!$B$13*E60,0) -> 0 | G60: =IF(15<=$B$7,IF(AND(ISNUMBER(F60),SUM(F46:F65)>0,Helpers!$B$13>0),F60*(Helpers!$B$13/SUM(F46:F65)),0),0) -> 0 | H60: =IF(15<=$B$7,C60*G60,0) -> 0 | I60: =IF(15<=$B$7,H60+I59,0) -> 0 | J60: =IF(15<=$B$7,G60+J59,0) -> 0 | K60: =IF(15<=$B$7,IF(J60>0,I60/J60,0),0) -> 0 | L60: =IF(AND(A60<=$B$7,C60>0,G60>0,ISNUMBER(C60),ISNUMBER(G60)),"Yes","No") -> No
A61: 16 | B61: =IF(16<=$B$7,Helpers!$B$10+Helpers!$B$7*(16-1),0) -> 0 | C61: =IF(16<=$B$7,MAX(B61*Helpers!$B$19,Helpers!$B$20+Helpers!$B$7*(16-1)),0) -> 0 | D61: =IF(16<=$B$7,EXP(2*(16-1)/(IF($B$7>1,$B$7-1,1))),0) -> 0 | E61: =IF(16<=$B$7,IF(SUM(D46:D65)>0,D61/SUM(D46:D65),0),0) -> 0 | F61: =IF(16<=$B$7,Helpers!$B$13*E61,0) -> 0 | G61: =IF(16<=$B$7,IF(AND(ISNUMBER(F61),SUM(F46:F65)>0,Helpers!$B$13>0),F61*(Helpers!$B$13/SUM(F46:F65)),0),0) -> 0 | H61: =IF(16<=$B$7,C61*G61,0) -> 0 | I61: =IF(16<=$B$7,H61+I60,0) -> 0 | J61: =IF(16<=$B$7,G61+J60,0) -> 0 | K61: =IF(16<=$B$7,IF(J61>0,I61/J61,0),0) -> 0 | L61: =IF(AND(A61<=$B$7,C61>0,G61>0,ISNUMBER(C61),ISNUMBER(G61)),"Yes","No") -> No
A62: 17 | B62: =IF(17<=$B$7,Helpers!$B$10+Helpers!$B$7*(17-1),0) -> 0 | C62: =IF(17<=$B$7,MAX(B62*Helpers!$B$19,Helpers!$B$20+Helpers!$B$7*(17-1)),0) -> 0 | D62: =IF(17<=$B$7,EXP(2*(17-1)/(IF($B$7>1,$B$7-1,1))),0) -> 0 | E62: =IF(17<=$B$7,IF(SUM(D46:D65)>0,D62/SUM(D46:D65),0),0) -> 0 | F62: =IF(17<=$B$7,Helpers!$B$13*E62,0) -> 0 | G62: =IF(17<=$B$7,IF(AND(ISNUMBER(F62),SUM(F46:F65)>0,Helpers!$B$13>0),F62*(Helpers!$B$13/SUM(F46:F65)),0),0) -> 0 | H62: =IF(17<=$B$7,C62*G62,0) -> 0 | I62: =IF(17<=$B$7,H62+I61,0) -> 0 | J62: =IF(17<=$B$7,G62+J61,0) -> 0 | K62: =IF(17<=$B$7,IF(J62>0,I62/J62,0),0) -> 0 | L62: =IF(AND(A62<=$B$7,C62>0,G62>0,ISNUMBER(C62),ISNUMBER(G62)),"Yes","No") -> No
A63: 18 | B63: =IF(18<=$B$7,Helpers!$B$10+Helpers!$B$7*(18-1),0) -> 0 | C63: =IF(18<=$B$7,MAX(B63*Helpers!$B$19,Helpers!$B$20+Helpers!$B$7*(18-1)),0) -> 0 | D63: =IF(18<=$B$7,EXP(2*(18-1)/(IF($B$7>1,$B$7-1,1))),0) -> 0 | E63: =IF(18<=$B$7,IF(SUM(D46:D65)>0,D63/SUM(D46:D65),0),0) -> 0 | F63: =IF(18<=$B$7,Helpers!$B$13*E63,0) -> 0 | G63: =IF(18<=$B$7,IF(AND(ISNUMBER(F63),SUM(F46:F65)>0,Helpers!$B$13>0),F63*(Helpers!$B$13/SUM(F46:F65)),0),0) -> 0 | H63: =IF(18<=$B$7,C63*G63,0) -> 0 | I63: =IF(18<=$B$7,H63+I62,0) -> 0 | J63: =IF(18<=$B$7,G63+J62,0) -> 0 | K63: =IF(18<=$B$7,IF(J63>0,I63/J63,0),0) -> 0 | L63: =IF(AND(A63<=$B$7,C63>0,G63>0,ISNUMBER(C63),ISNUMBER(G63)),"Yes","No") -> No
A64: 19 | B64: =IF(19<=$B$7,Helpers!$B$10+Helpers!$B$7*(19-1),0) -> 0 | C64: =IF(19<=$B$7,MAX(B64*Helpers!$B$19,Helpers!$B$20+Helpers!$B$7*(19-1)),0) -> 0 | D64: =IF(19<=$B$7,EXP(2*(19-1)/(IF($B$7>1,$B$7-1,1))),0) -> 0 | E64: =IF(19<=$B$7,IF(SUM(D46:D65)>0,D64/SUM(D46:D65),0),0) -> 0 | F64: =IF(19<=$B$7,Helpers!$B$13*E64,0) -> 0 | G64: =IF(19<=$B$7,IF(AND(ISNUMBER(F64),SUM(F46:F65)>0,Helpers!$B$13>0),F64*(Helpers!$B$13/SUM(F46:F65)),0),0) -> 0 | H64: =IF(19<=$B$7,C64*G64,0) -> 0 | I64: =IF(19<=$B$7,H64+I63,0) -> 0 | J64: =IF(19<=$B$7,G64+J63,0) -> 0 | K64: =IF(19<=$B$7,IF(J64>0,I64/J64,0),0) -> 0 | L64: =IF(AND(A64<=$B$7,C64>0,G64>0,ISNUMBER(C64),ISNUMBER(G64)),"Yes","No") -> No
A65: 20 | B65: =IF(20<=$B$7,Helpers!$B$10+Helpers!$B$7*(20-1),0) -> 0 | C65: =IF(20<=$B$7,MAX(B65*Helpers!$B$19,Helpers!$B$20+Helpers!$B$7*(20-1)),0) -> 0 | D65: =IF(20<=$B$7,EXP(2*(20-1)/(IF($B$7>1,$B$7-1,1))),0) -> 0 | E65: =IF(20<=$B$7,IF(SUM(D46:D65)>0,D65/SUM(D46:D65),0),0) -> 0 | F65: =IF(20<=$B$7,Helpers!$B$13*E65,0) -> 0 | G65: =IF(20<=$B$7,IF(AND(ISNUMBER(F65),SUM(F46:F65)>0,Helpers!$B$13>0),F65*(Helpers!$B$13/SUM(F46:F65)),0),0) -> 0 | H65: =IF(20<=$B$7,C65*G65,0) -> 0 | I65: =IF(20<=$B$7,H65+I64,0) -> 0 | J65: =IF(20<=$B$7,G65+J64,0) -> 0 | K65: =IF(20<=$B$7,IF(J65>0,I65/J65,0),0) -> 0 | L65: =IF(AND(A65<=$B$7,C65>0,G65>0,ISNUMBER(C65),ISNUMBER(G65)),"Yes","No") -> No
A71: INSTRUCTIONS
A72: 1. Enter your parameters in the INPUT PARAMETERS section at the top.
A73: 2. Review the SUMMARY RESULTS to see total cost, revenue, and profit.
A74: 3. Check the 'Helpers' sheet for validation checks and detailed calculations.
A75: 4. View BUY ORDERS and SELL ORDERS tables below.
A76: 5. Filters are applied automatically - only active rungs are shown.
A77: 6. See the Charts sheet for visualizations.
A78: 7. Helper calculations are in the 'Helpers' sheet (protected from modification).

Sheet Helpers
A1: HELPER CALCULATIONS
A2: ⚠ WARNING: These cells are protected. Modifying them may cause calculation errors.
A4: Buy Price Helpers
A5: Buy Upper | B5: =Calculator!$B$5 -> 50
A6: Buy Lower | B6: =IF(Calculator!$B$5>0,Calculator!$B$5*(1-Calculator!$B$8/100),0) -> 35
A7: Price Step | B7: =IF(AND(Calculator!$B$7>1,B5>0,B6>0),(B5-B6)/(Calculator!$B$7-1),IF(Calculator!$B$5>0,Calculator!$B$5*0.1,0)) -> 1.6666667
A8: Max Buy Price | B8: =Calculator!$B$5 -> 50
A9: Gap Size | B9: =IF(AND(B8>0,B7>0),MAX(1,CEILING(B8*Calculator!$B$6/100*0.5/B7,1))*B7,0) -> 20
A10: Min Sell Price | B10: =IF(AND(B8>0,B9>0),B8+B9,0) -> 70
A12: Buy Order Totals
A13: Total Buy Qty | B13: =SUM(Calculator!G21:G40) -> 254.81114
A14: Total Cost | B14: =SUM(Calculator!F21:F40) -> 10000
A15: Target Revenue | B15: =B14*(1+Calculator!$B$6/100) -> 17500
A17: Sell Order Helpers
A18: Initial Revenue | B18: =SUMPRODUCT(Calculator!B46:B65,Calculator!G46:G65) -> 20468.506
A19: Price Scale | B19: =IF(AND(B18>0,Helpers!$B$15>0),Helpers!$B$15/B18,1) -> 0.85497203
A20: Min Valid Sell | B20: =IF(AND(Helpers!$B$8>0,Helpers!$B$7>0),Helpers!$B$8+Helpers!$B$7,0) -> 51.666667
A22: Validation Checks
A23: Budget > 0 | B23: =IF(Calculator!$B$4>0,"✓ OK","✗ ERROR: Budget must be positive") -> ✓ OK
A24: Current Price > 0 | B24: =IF(Calculator!$B$5>0,"✓ OK","✗ ERROR: Price must be positive") -> ✓ OK
A25: Profit Target Valid | B25: =IF(AND(Calculator!$B$6>=10,Calculator!$B$6<=200),"✓ OK","✗ ERROR: Profit target must be 10-200%") -> ✓ OK
A26: Num Rungs >= 1 | B26: =IF(Calculator!$B$7>=1,"✓ OK","✗ ERROR: Number of rungs must be at least 1") -> ✓ OK
A27: Buy Price Range Valid | B27: =IF(AND(Calculator!$B$8>0,Calculator!$B$8<=100),"✓ OK","✗ ERROR: Buy price range must be 0-100%") -> ✓ OK
A28: Buy Lower > 0 | B28: =IF(Helpers!$B$6>0,"✓ OK","✗ ERROR: Buy lower price is non-positive. Reduce Buy Price Range %") -> ✓ OK
A29: Sell Prices > Buy Prices | B29: =IF(AND(Calculator!$B$7>0,Calculator!$B$7<=20,SUM(Calculator!B21:B40)>0,SUM(Calculator!C46:C65)>0),IF(AND(ISNUMBER(INDEX(Calculator!C46:C65,1)),ISNUMBER(INDEX(Calculator!B21:B40,Calculator!$B$7))),IF(INDEX(Calculator!C46:C65,1)>INDEX(Calculator!B21:B40,Calculator!$B$7),"✓ OK","✗ ERROR: Sell prices must exceed buy prices"),"N/A"),"N/A") -> ✓ OK
A30: Volume Match | B30: =IF(ABS(Helpers!$B$13-SUM(Calculator!G46:G65))<0.0001,"✓ OK","⚠ WARNING: Buy and sell quantities do not match exactly") -> ✓ OK

Sheet Charts
